Workbook

Sheet README
A1: STORM SPLIT — Balance Model
A2: Single source of truth for every number in the game. Verse reads constants exported from here.
A5: HOW TO USE
A6: Blue cells | B6: Inputs and levers. These are the ONLY cells you edit. Change one and everything recalculates.
A7: Black cells | B7: Formulas. Do not overwrite — you will silently break the model.
A8: Green cells | B8: Links pulling a value from another sheet.
A9: Yellow fill | B9: Key assumptions worth arguing about before you build anything on them.
A11: SHEETS
A12: Tuning | B12: Master knobs. Start here. Almost every number downstream derives from this sheet.
A13: Towers | B13: The 5 base towers: purchase cost, damage, fire rate, range, whether they hit air.
A14: Tower Upgrades | B14: 75 rows — 5 towers x 3 paths x 5 tiers. Costs and stat multipliers per tier.
A15: Heroes | B15: 3 free heroes (Pistol, Assault Rifle, Shotgun): base gun and ability. Hero Upgrades: 3 paths x 5 tiers each.
A16: Mastery | B16: 20 permanent levels per hero, bought with Amber. Cheaper upgrades, cooldowns, head starts — never damage.
A17: Enemies | B17: The splitting ladder. Effective HP is the important derived column — read its note.
A18: Rounds | B18: All 40 rounds: composition, income, required DPS.
A19: Balance Check | B19: The validator. Tells you which rounds are unwinnable. Check this after every change.
A21: WORKFLOW
A22: 1 | B22: Tune a lever on the Tuning sheet.
A23: 2 | B23: Open Balance Check. Any round flagged TIGHT is one the player probably cannot afford to clear.
A24: 3 | B24: Adjust and repeat. Do not tune individual rounds until the curve is right.
A25: 4 | B25: Export the settled constants into the Verse constants file. Never hardcode a number in behavior scripts.
A27: WARNING
A28: Seeded values | B28: Every number here is a defensible starting point, not a tested one. They came from design
B29: reasoning, not playtesting. Expect to change most of them once the game is playable.

Sheet Tuning
A1: TUNING — master levers
A2: Every blue cell here drives the rest of the workbook. Change these, not the downstream sheets.
A4: Lever | B4: Value | C4: Unit | D4: What it controls
A5: ECONOMY
A6: Starting cash | B6: 450 | C6: cash | D6: Default: what players have before round 1 on Easy. Each level's own is Difficulty → Starting cash; the exporter checks Easy equals this.
A7: Starting lives | B7: 40 | C7: lives | D7: Not used by the game: lives come from Difficulty → Starting lives (Easy 40).
A8: Cash per effective HP | B8: 0.43 | C8: cash | D8: Cash per point of enemy HP destroyed, counting every split layer. Solved to make late rounds tight.
A9: Round bonus base | B9: 60 | C9: cash | D9: Flat end-of-round payment.
A10: Round bonus per round | B10: 1 | C10: cash | D10: Added per round number, so round 30 pays base + 30.
A11: TOWERS
A12: Tier cost growth | B12: 2.3 | C12: x | D12: Each upgrade tier costs this multiple of the tower's base cost, compounding.
A13: Tier damage growth | B13: 1.9 | C13: x | D13: Baseline damage multiple per tier before path character is applied.
A14: Sell refund | B14: 0.7 | C14: fraction | D14: Fraction of cash spent returned when selling a tower.
A15: ENEMIES
A16: Global HP scalar | B16: 1 | C16: x | D16: Multiplies every enemy's base HP. The fastest single difficulty dial.
A17: Round HP ramp | B17: 1.052 | C17: x | D17: Enemy HP compounds by this much per round. THIS is what makes late rounds hard, not enemy count.
A18: Max concurrent enemies | B18: 130 | C18: count | D18: Hard ceiling on a round's spawn count. Set by UEFN performance, not by design. Validate in phase 1.
A19: Global speed scalar | B19: 1 | C19: x | D19: Multiplies every enemy's speed.
A20: PLAYER
A21: Hero upgrade base cost | B21: 200 | C21: cash | D21: Tier 1 of any hero path. Picking a hero is free.
A22: Hero upgrade cost growth | B22: 2 | C22: x | D22: Each hero upgrade tier costs this multiple of the one before.
A24: PROGRESSION
A25: Multiplayer loss payout | B25: 5 | C25: amber | D25: Every player in a multiplayer match that ends without a clear. Clears pay the Difficulty sheet reward; solo losses pay nothing.
A26: Typical amber per match | B26: 50 | C26: amber | D26: Planning estimate only (Mastery "Matches to earn"). Not paid out by the game.
A27: Mastery cost base | B27: 25 | C27: amber | D27: Cost of mastery level 1.
A28: Mastery cost growth | B28: 1.18 | C28: x | D28: Compounding cost per mastery level to 20.
A29: VALIDATION
A30: Assumed spend on towers | B30: 0.75 | C30: fraction | D30: Share of cumulative cash a competent player puts into tower DPS.
A31: Expected efficiency | B31: 0.6 | C31: fraction | D31: Share of theoretical DPS actually landing, after targeting and travel-time losses.
A32: Rounds per tier | B32: 8 | C32: rounds | D32: How fast the reference build climbs tiers. Drives the rising cost per DPS.
A34: ABILITIES
A35: Line pierce reach | B35: 30 | C35: studs | D35: How far behind its target a line-piercing shot keeps hitting.
A36: Mark duration | B36: 3 | C36: s | D36: How long a Spotter mark lasts on an enemy.
A37: Bomblet damage | B37: 0.5 | C37: fraction | D37: Each cluster bomblet deals this share of the shell's damage.
A38: Bomblet spread | B38: 5 | C38: studs | D38: How far bomblets scatter from the shell.
A40: CO-OP
A41: Extra enemies per player | B41: 0.35 | C41: x | D41: Enemy count x grows by this for each player beyond the first (10 players = x4.15).
A42: Extra HP per player | B42: 0.08 | C42: x | D42: Enemy HP x grows by this for each player beyond the first.
A43: Starting cash per extra player | B43: 200 | C43: cash | D43: Added to the shared pot once for each player beyond the first, whenever they join.
A45: HERO
A46: Weapon aim assist | B46: 3 | C46: studs | D46: A shot hits the enemy nearest its (recoil-spread) ray, if one is this close to it.
A47: Overdrive fire rate x | B47: 2 | C47: x | D47: Your own fire rate during Overdrive.
A48: Spin-up time | B48: 2 | C48: s | D48: Holding the trigger this long takes Spin-Up to full speed.
A49: Ricochet reach | B49: 12 | C49: studs | D49: How far a ricochet can jump to the next enemy.
A50: Still speed | B50: 1 | C50: studs/s | D50: Moving slower than this counts as standing still (Bipod).
A51: Airburst reach | B51: 50 | C51: studs | D51: How far from you an Airburst can be called in.
A52: Airburst delay | B52: 1 | C52: s | D52: Time between calling an Airburst and the strike landing.
A54: QUARTERMASTER / CHILLER
A55: Chest lifetime | B55: 20 | C55: s | D55: Airdrop chests vanish if nobody collects them in time.
A56: Chest spread | B56: 25 | C56: studs | D56: Chests land this far around their Quartermaster at most.
A58: HERO LEVELS
A59: Rounds per level | B59: 5 | C59: rounds | D59: Every this many rounds cleared, heroes level up and towers get stronger. (Later: hero XP from pops.)
A60: Hero damage per level | B60: 0.25 | C60: x | D60: Each hero level multiplies all hero damage by 1 + this (compounding).
A61: Tower damage per level | B61: 0.1 | C61: x | D61: Each level multiplies all tower damage by 1 + this (compounding).
A63: MATCH FLOW
A64: Respawn time | B64: 3 | C64: s | D64: How long after dying a player respawns during a match.
A65: Results time | B65: 8 | C65: s | D65: How long the result screen shows before everyone returns home.
A67: PLAYER HEALTH / COMBAT
A68: Player max health | B68: 100 | C68: HP | D68: Every player's health. Fixed: harder rounds hurt through tougher dinos, not bigger numbers.
A69: Heal per round | B69: 25 | C69: HP | D69: Every living player heals this much when a round is cleared (capped at max).
A70: Spawn protection | B70: 3 | C70: s | D70: A force field on respawn, so a player isn't bitten again the instant they're back.
A71: Max resist | B71: 60 | C71: % | D71: Damage resistance never goes above this. Sources don't stack: the strongest wins.
A72: Max projectiles | B72: 80 | C72: count | D72: Dino projectiles in flight at once; past this the oldest is dropped.
A73: Tower HP per tier | B73: 0.15 | C73: x base | D73: Each upgrade tier bought (any path) adds this share of the tower's base max HP.
A74: Repair cost | B74: 0.3 | C74: x spent | D74: Repairing a tower from 0 HP costs this share of the cash put into it (less for partial damage).
A75: Burn patch min reach | B75: 3 | C75: studs | D75: Burning ground is at least this wide either side, so a hero patch with no splash (Incendiary) is visible.
A76: Boss jaw lock x | B76: 0.5 | C76: x | D76: A boss hit by Jaw Lock is locked this share of the lock time (bosses also ignore the Medic slow).
A78: REWARDS
A79: Daily bounties | B79: 3 | C79: count | D79: Daily bounties on the Hunt Board. Slots fill in the order easy, medium, hard, so 3 = one of each (DECISIONS #65).
A80: Weekly bounties | B80: 3 | C80: count | D80: Weekly bounties on the Hunt Board, filled the same way.
A81: Daily swaps | B81: 1 | C81: count | D81: Free swaps a day, only on an unfinished bounty; the new one comes from the same slot (DECISIONS #67).
A82: Weekly swaps | B82: 1 | C82: count | D82: Free swaps a week on the weekly bounties.
A83: Haul resets after missed days | B83: 0 | C83: days | D83: 0 = never: a missed day only pauses the Daily Haul. 1 = miss one day and it starts again at day 1 (DECISIONS #64).
A84: Daily reset hour UTC | B84: 0 | C84: hour | D84: The hour (0-23, UTC) a new day starts for the Daily Haul and the daily bounties (DECISIONS #68).
A85: Weekly reset day | B85: 1 | C85: day | D85: The day the weekly bounties reset, at the daily reset hour: 1 = Monday ... 7 = Sunday.
A87: HERO XP
A88: XP per level | B88: 500 | C88: XP | D88: XP for one hero level: level = 1 + XP / this, rounded down. Must be a whole multiple of Rounds per level, so a cleared round is worth a whole Round XP (DECISIONS #100).
A89: XP per pop | B89: 0.25 | C89: XP | D89: Pop XP for each take-down credited to the hunter (gun, towers, fire). Pending until the round is cleared.
A90: Pop XP cap per round | B90: 15 | C90: XP | D90: The most pop XP one round can bank. 0 = the old every-5-rounds curve exactly.
A91: Team pop share | B91: 0.25 | C91: x | D91: Share of teammates' take-downs that counts toward your pop XP (DECISIONS #102). 0 = own only, 1 = fully shared.
A92: Hero level lead cap | B92: 1 | C92: levels | D92: A hunter is never more than this many levels above the round level (DECISIONS #101). The export fails if the seeds alone would beat it.
A94: MASTERY PERKS
A95: Mastery perk worth cap | B95: 40 | C95: % | D95: The most a mastery perk may be worth, in % of one cast (Mastery Perks sheet, DECISIONS #99). Read by the exporter only.
A97: BOSS THROWS
A98: Boss ranged vs towers x | B98: 0.3 | C98: x | D98: A Boss species' projectile damage to a tower is multiplied by this; hunters take full damage (they can dodge). DECISIONS #138, #154. 1 = off.
A100: PIERCE-THROUGH
A101: Break level step | B101: 3 | C101: levels | D101: Raw-damage tiers (Size breaks 2+) break one more size per this many tower levels above 1: +1 at level 4, +2 at level 7. Heroes never. DECISIONS #126.
A102: Max size breaks | B102: 4 | C102: sizes | D102: The most sizes one hit may drop (pierce-through cap). 1 = off everywhere. DECISIONS #126.
A104: PLAYER LEVEL
A105: Player XP base | B105: 500 | C105: XP | D105: Player level 1 -> 2 costs this much player XP (DECISIONS #120). Saved between matches; rewards are cosmetic only.
A106: Player XP step | B106: 50 | C106: XP | D106: Each player level costs this much more than the one before: level n -> n+1 = base + step x (n-1) (DECISIONS #120).
A107: Player XP per level max | B107: 10000 | C107: XP | D107: No player level costs more than this (reached at level 191 with the seeds); levels never end (DECISIONS #120).
A108: Solo take-down XP x | B108: 2 | C108: x | D108: In solo, the take-down part of the match's hero XP counts this many times toward player XP only; co-op and the hunter level are unchanged (DECISIONS #124). 1 = off.
A110: STORM COIL
A111: Coil arcs | B111: 4 | C111: arcs after the first hit (Copper Wire raises it)
A112: Coil arc reach | B112: 10 | C112: studs from one dino to the next
A113: Coil arc falloff | B113: 0.8 | C113: each arc x this of the last
A114: Power Grid range per coil | B114: 0.15 | C114: range x (1 + this x (n - 1)), DECISIONS #151
A115: Power Grid damage base | B115: 0.5 | C115: damage x (base + per coil x n)
A116: Power Grid damage per coil | B116: 0.25
...

Sheet Towers
A1: TOWERS — base stats
A2: Purchase cost and tier-0 stats. Upgrade scaling lives on the Tower Upgrades sheet.
A4: Tower | B4: Role | C4: Cost | D4: Damage | E4: Fire rate /s | F4: Targets hit | G4: Base DPS | H4: Range (m) | I4: Hits air | J4: Income/round | K4: Design note | L4: Splash radius (m) | M4: Slow % | N4: Unlock cost (amber) | O4: Key | P4: Max HP | Q4: Heal /s | R4: Resist % | S4: Upgrade cost growth | T4: Untouchable | U4: On track | V4: Chains | W4: Birds | X4: Harpoons | Y4: Resin | Z4: Walkers
A5: Hunting Blind | B5: Cheap single-target DPS | C5: 200 | D5: 1 | E5: 3 | F5: 1 | G5: {=D5*E5*F5} | H5: 20 | I5: Yes | J5: 0 | K5: Spam early, never stop buying. The DPS baseline everything else is measured against. | L5: 0 | M5: 0 | N5: 0 | O5: SCOUT | P5: 100 | Q5: 0 | R5: 0
A6: Longshot Perch | B6: Global range, slow | C6: 350 | D6: 9 | E6: 0.45 | F6: 1 | G6: {=D6*E6*F6} | H6: 999 | I6: Yes | J6: 0 | K6: Range covers the whole map. Your answer to anything the ground towers cannot reach. | L6: 0 | M6: 0 | N6: 0 | O6: SNIPER | P6: 80 | Q6: 0 | R6: 0
A7: Mortar Pit | B7: Area damage, ground only | C7: 550 | D7: 5 | E7: 1 | F7: 3 | G7: {=D7*E7*F7} | H7: 18 | I7: No | J7: 0 | K7: Targets hit = average enemies caught per blast. Cannot hit air at all, by design. | L7: 6 | M7: 0 | N7: 0 | O7: GRENADIER | P7: 150 | Q7: 0 | R7: 0
A8: Tranq Station | B8: Tranquilizer darts: slows and knocks out | C8: 400 | D8: 0.5 | E8: 1 | F8: 4 | G8: {=D8*E8*F8} | H8: 12 | I8: Yes | J8: 0 | K8: Damage is nearly irrelevant. Its value is the slow, which multiplies every tower nearby. | L8: 6 | M8: 40 | N8: 100 | O8: CHILLER | P8: 120 | Q8: 0 | R8: 0
A9: Supply Camp | B9: Economy, no attack | C9: 1000 | D9: 0 | E9: 0 | F9: 0 | G9: {=D9*E9*F9} | H9: 20 | I9: No | J9: 150 | K9: Never shoots. Decides whether round 35 is affordable. | L9: 0 | M9: 0 | N9: 150 | O9: QUARTERMASTER | P9: 200 | Q9: 0 | R9: 0 | S9: 1.6
A10: Field Hospital | B10: Support: heals towers and hunters, no attack | C10: 450 | D10: 0 | E10: 0 | F10: 0 | G10: {=D10*E10*F10} | H10: 15 | I10: No | J10: 0 | K10: Never shoots. Heals standing towers and hunters in range; its paths revive trampled towers, drop med kits and toughen towers. | L10: 0 | M10: 0 | N10: 100 | O10: HOSPITAL | P10: 150 | Q10: 3 | R10: 0
A11: Armory | B11: Defence: damage resistance, no attack | C11: 600 | D11: 0 | E11: 0 | F11: 0 | G11: {=D11*E11*F11} | H11: 15 | I11: No | J11: 0 | K11: Never shoots. Towers and hunters in range take less damage; its paths add thorns, tower buffs and hunter handling. | L11: 0 | M11: 0 | N11: 150 | O11: ARMORY | P11: 250 | Q11: 0 | R11: 15
A13: Cost per DPS (Scout baseline) | C13: {=C5/G5} | D13: Cash needed to buy 1 DPS at tier 0. Balance Check uses this.
A15: Storm Coil | B15: Chain lightning: crowds and air | C15: 400 | D15: 6 | E15: 1 | F15: 1 | G15: =D15*E15*F15 | H15: 14 | I15: Yes | J15: 0 | K15: Each strike arcs from dino to dino (falloff per arc, breaks 1). Short own range. TOWERS_NEXT.md. | L15: 0 | M15: 0 | N15: 300 | O15: COIL | P15: 150 | Q15: 0 | R15: 0 | V15: Yes
A16: Falcon Roost | B16: Birds of prey: huge range, can't be damaged | C16: 400 | D16: 3 | E16: 1.33 | F16: 1 | G16: =D16*E16*F16 | H16: 40 | I16: Yes | J16: 0 | K16: Falcons fly out, dive and return. No HP: dinos ignore it, never repaired (DECISIONS #148). | L16: 0 | M16: 0 | N16: 200 | O16: FALCON | P16: 0 | Q16: 0 | R16: 0 | T16: Yes | W16: 2
A17: Tar Pit | B17: Tar on the track: slows and sinks, can't be damaged | C17: 450 | D17: 0 | E17: 0 | F17: 0 | G17: =D17*E17*F17 | H17: 12 | I17: No | J17: 0 | K17: Placed ON the track (DECISIONS #152); Range = the pool's length of track. No HP (#148). | L17: 0 | M17: 25 | N17: 250 | O17: TARPIT | P17: 0 | Q17: 0 | R17: 0 | T17: Yes | U17: Yes
A18: Harpoon Ballista | B18: The heaviest single hit: pierce-through | C18: 500 | D18: 12 | E18: 0.5 | F18: 1 | G18: =D18*E18*F18 | H18: 24 | I18: Yes | J18: 0 | K18: One heavy bolt every 2.5 s; its Spearhead path breaks several sizes (pierce-through). | L18: 0 | M18: 0 | N18: 300 | O18: BALLISTA | P18: 150 | Q18: 0 | R18: 0 | X18: Yes
A19: Amber Resin Cannon | B19: Control: resin slows, entombs and fossilizes | C19: 800 | D19: 2 | E19: 1 | F19: 1 | G19: =D19*E19*F19 | H19: 18 | I19: No | J19: 0 | K19: Resin globs: slows, entombs (hard stop), fossils. TOWERS_LATER.md. | L19: 0 | M19: 0 | N19: 500 | O19: RESIN | P19: 150 | Q19: 0 | R19: 0 | Y19: Yes
A20: Raptor Pen | B20: Tamed raptors: they run out, bite and come back | C20: 600 | D20: 10 | E20: 2.3 | F20: 1 | G20: =D20*E20*F20 | H20: 22 | I20: No | J20: 0 | K20: Tamed raptors sprint out, pounce, bite and come back; they can be bitten. TOWERS_LATER.md. | L20: 0 | M20: 0 | N20: 500 | O20: RAPTOR | P20: 150 | Q20: 0 | R20: 0 | Z20: 1
A21: Bone Totem | B21: Bones charge it: a roar, buffs or cash | C21: 600 | D21: 60 | E21: 0 | F21: 1 | G21: =D21*E21*F21 | H21: 24 | I21: Yes | J21: 0 | K21: Bones taken near it charge it; full = Spirit Roar (area, breaks 2). Never adds Bones to any score. TOWERS_LATER.md. | L21: 0 | M21: 0 | N21: 450 | O21: TOTEM | P21: 200 | Q21: 0 | R21: 0

Sheet Tower Upgrades
A1: TOWER UPGRADES — 11 towers x 3 paths x 5 tiers
A2: Multipliers are blue because they define each path's character. Costs are formulas off Tuning. Range x multiplies the tower's base range (range-focus paths only). Name is the tier's in-game name (full design: UPGRADES.md). Columns from 'Pierces armour' on are ability values, cumulative per tier; blank = none. A/B/C (PLAN Phase 9, DECISIONS #275): tiers 1-3 rows are cumulative; a tier-4 or tier-5 row is one option (Option A/B/C, Blurb = its card line, max 60 chars) and holds ONLY ITS OWN STEP over the tier below (x columns multiply, amounts take the higher, flags add, overrides replace; blank = no change). The exporter composes every build. New options are appended at the bottom.
A4: Tower | B4: Path | C4: Path focus | D4: Tier | E4: Upgrade cost | F4: Cumulative cost | G4: Damage x | H4: Rate x | I4: Targets x | J4: Resulting DPS | K4: Cost per DPS | L4: Range x | M4: Name | N4: Pierces armour | O4: Armoured x | P4: Boss x | Q4: Shots | R4: Line hits | S4: Splash x | T4: Mark % | U4: Stun (s) | V4: Stuns bosses | W4: Knockback (studs) | X4: Burn DPS | Y4: Burn (s) | Z4: Bomblets | AA4: Bomblet generations | AB4: Aura rate % | AC4: Aura damage % | AD4: Aura pierces armour | AE4: Slow % | AF4: Slow linger (s) | AG4: Slows bosses | AH4: Freeze every (s) | AI4: Freeze (s) | AJ4: Freeze damage | AK4: Freeze holds bosses | AL4: Brittle % | AM4: Strips armour | AN4: Income x | AO4: Interest % | AP4: Interest cap | AQ4: Chests | AR4: Chest cash | AS4: Upgrade discount % | AT4: Sell refund | AU4: Resist % | AV4: Thorns damage | AW4: Stuns biters (s) | AX4: Hunter recoil x | AY4: Hunter reload x | AZ4: Hunter spread x | BA4: Hunter fire rate % | BB4: Heal x | BC4: Revives | BD4: Revive speed x | BE4: Med kits | BF4: Med kit heal | BG4: Rescue beacon (respawn x) | BH4: Aura HP % | BI4: Last stand | BJ4: Size breaks | BK4: Arcs | BL4: Arc reach | BM4: Arc forks | BN4: Arc jumps | BO4: Power grid | BP4: Static % | BQ4: Judgement bolt | BR4: Grounding every (s) | BS4: Aura arc % | BT4: Birds | BU4: First dive x | BV4: Eagle | BW4: Murmuration | BX4: Boss mark % | BY4: Dive aura rate % | BZ4: Skewer | CA4: Tow line | CB4: Chain harpoons | CC4: Sink seconds | CD4: Sink cash | CE4: Sink chest cash | CF4: Eruption | CG4: Tracks slow % | CH4: Aura vs slowed % | CI4: Option | CJ4: Blurb | CK4: PvP effect | CL4: Raider slow % | CM4: Raider slow (s) | CN4: Raider damage | CO4: Bounty cash | CP4: Biter slow % | CQ4: Biter slow (s) | CR4: Field strike every (s) | CS4: Field strike x | CT4: Chain effects | CU4: Targets biggest | CV4: Entomb (s) | CW4: Entomb hits x | CX4: Entomb amp % | CY4: Entomb spread | CZ4: Entomb slow % | DA4: Entomb all every (s) | DB4: Boss entomb (s) | DC4: Send back (studs) | DD4: Fossil below % | DE4: Fossil rate % | DF4: Bounty fossils x | DG4: Heart every (fossils) | DH4: Seal (s) | DI4: Seal every (s) | DJ4: Seal heal % | DK4: Reflect damage | DL4: Wall (s) | DM4: Take-down mark % | DN4: Walkers | DO4: Walker HP x | DP4: Walker speed x | DQ4: Walker resist % | DR4: Walker respawn x | DS4: Hold (s) | DT4: Boss hold (s) | DU4: Flanking | DV4: Targets first | DW4: Hits air | DX4: Heals between rounds | DY4: Dodge | DZ4: Alpha | EA4: Swarm | EB4: Charge | EC4: Guard | ED4: Stun roar every (s) | EE4: Take-down stack % | EF4: Avenger x | EG4: Hunter damage % | EH4: Charge x | EI4: Hunter charge x | EJ4: Boss charge % | EK4: Bounty charge x | EL4: Charge needed x | EM4: Roar echoes | EN4: Roar whole track | EO4: Skulls | EP4: Full guard (s) | EQ4: Spirit hunters | ER4: Full cash | ES4: Payday cash | ET4: Treasure | EU4: Charge aura damage % | EV4: Hunter ability cooldown x | EW4: Side aura half | EX4: Bone cash | EY4: Bank cash per charge | EZ4: Finishing roar | FA4: Aura range %
A5: Hunting Blind | B5: Lookout | C5: range | D5: 1 | E5: {=ROUND('Towers'!$C$5*POWER('Tuning'!$B$12,D5),0)} | F5: {='Towers'!$C$5+E5} | G5: 1.3 | H5: 1.15 | I5: 1 | J5: {='Towers'!$G$5*G5*H5*I5} | K5: {=IF(J5=0,0,F5/J5)} | L5: 1.15 | M5: Keen Eyes
A6: Hunting Blind | B6: Lookout | C6: range | D6: 2 | E6: {=ROUND('Towers'!$C$5*POWER('Tuning'!$B$12,D6),0)} | F6: {=F5+E6} | G6: 1.69 | H6: 1.32 | I6: 1 | J6: {='Towers'!$G$5*G6*H6*I6} | K6: {=IF(J6=0,0,F6/J6)} | L6: 1.3 | M6: Spyglass
A7: Hunting Blind | B7: Lookout | C7: range | D7: 3 | E7: {=ROUND('Towers'!$C$5*POWER('Tuning'!$B$12,D7),0)} | F7: {=F6+E7} | G7: 2.2 | H7: 1.52 | I7: 1 | J7: {='Towers'!$G$5*G7*H7*I7} | K7: {=IF(J7=0,0,F7/J7)} | L7: 1.5 | M7: Flare Gun | AB7: 10
A8: Hunting Blind | B8: Lookout | C8: range | D8: 4 | E8: {=ROUND('Towers'!$C$5*POWER('Tuning'!$B$12,D8),0)} | F8: {=F7+E8} | G8: 1.3 | H8: 1.1513158 | I8: 1 | J8: {='Towers'!$G$5*G8*H8*I8} | K8: {=IF(J8=0,0,F8/J8)} | L8: 1.1666667 | M8: Watch Post | CI8: A | CJ8: Sees further, and shoots faster and harder
A9: Hunting Blind | B9: Lookout | C9: range | D9: 5 | E9: {=ROUND('Towers'!$C$5*POWER('Tuning'!$B$12,D9),0)} | F9: {=F8+E9} | G9: 1.2972028 | H9: 1.1485714 | I9: 1 | J9: {='Towers'!$G$5*G9*H9*I9} | K9: {=IF(J9=0,0,F9/J9)} | L9: 1.1428571 | M9: Signal Tower | AC9: 20 | AD9: Yes | CI9: A | CJ9: Towers in range hit harder and can hurt armour
A10: Hunting Blind | B10: Trigger Happy | C10: rate | D10: 1 | E10: {=ROUND('Towers'!$C$5*POWER('Tuning'!$B$12,D10),0)} | F10: {='Towers'!$C$5+E10} | G10: 1.35 | H10: 1.42 | I10: 1 | J10: {='Towers'!$G$5*G10*H10*I10} | K10: {=IF(J10=0,0,F10/J10)} | L10: 1 | M10: Quick Hands
A11: Hunting Blind | B11: Trigger Happy | C11: rate | D11: 2 | E11: {=ROUND('Towers'!$C$5*POWER('Tuning'!$B$12,D11),0)} | F11: {=F10+E11} | G11: 1.82 | H11: 2.02 | I11: 1 | J11: {='Towers'!$G$5*G11*H11*I11} | K11: {=IF(J11=0,0,F11/J11)} | L11: 1 | M11: Extended Mag
A12: Hunting Blind | B12: Trigger Happy | C12: rate | D12: 3 | E12: {=ROUND('Towers'!$C$5*POWER('Tuning'!$B$12,D12),0)} | F12: {=F11+E12} | G12: 2.46 | H12: 2.86 | I12: 1 | J12: {='Towers'!$G$5*G12*H12*I12} | K12: {=IF(J12=0,0,F12/J12)} | L12: 1 | M12: Double Tap | Q12: 2
A13: Hunting Blind | B13: Trigger Happy | C13: rate | D13: 4 | E13: {=ROUND('Towers'!$C$5*POWER('Tuning'!$B$12,D13),0)} | F13: {=F12+E13} | G13: 1.3495935 | H13: 1.4230769 | I13: 1 | J13: {='Towers'!$G$5*G13*H13*I13} | K13: {=IF(J13=0,0,F13/J13)} | L13: 1 | M13: Bullet Hose | CI13: A | CJ13: Fires much faster and hits harder
A14: Hunting Blind | B14: Trigger Happy | C14: rate | D14: 5 | E14: {=ROUND('Towers'!$C$5*POWER('Tuning'!$B$12,D14),0)} | F14: {=F13+E14} | G14: 1.3493976 | H14: 1.4176904 | I14: 1 | J14: {='Towers'!$G$5*G14*H14*I14} | K14: {=IF(J14=0,0,F14/J14)} | L14: 1 | M14: Lead Rain | Q14: 3 | CI14: A | CJ14: The fastest fire in the game
A15: Hunting Blind | B15: Hardliner | C15: damage | D15: 1 | E15: {=ROUND('Towers'!$C$5*POWER('Tuning'!$B$12,D15),0)} | F15: {='Towers'!$C$5+E15} | G15: 1.9 | H15: 1 | I15: 1 | J15: {='Towers'!$G$5*G15*H15*I15} | K15: {=IF(J15=0,0,F15/J15)} | L15: 1 | M15: Heavy Slugs
A16: Hunting Blind | B16: Hardliner | C16: damage | D16: 2 | E16: {=ROUND('Towers'!$C$5*POWER('Tuning'!$B$12,D16),0)} | F16: {=F15+E16} | G16: 3.61 | H16: 1 | I16: 1 | J16: {='Towers'!$G$5*G16*H16*I16} | K16: {=IF(J16=0,0,F16/J16)} | L16: 1 | M16: Armor Breaker | N16: Yes
A17: Hunting Blind | B17: Hardliner | C17: damage | D17: 3 | E17: {=ROUND('Towers'!$C$5*POWER('Tuning'!$B$12,D17),0)} | F17: {=F16+E17} | G17: 6.86 | H17: 1 | I17: 1 | J17: {='Towers'!$G$5*G17*H17*I17} | K17: {=IF(J17=0,0,F17/J17)} | L17: 1 | M17: Hollow Points | N17: Yes | O17: 2
A18: Hunting Blind | B18: Hardliner | C18: damage | D18: 4 | E18: {=ROUND('Towers'!$C$5*POWER('Tuning'!$B$12,D18),0)} | F18: {=F17+E18} | G18: 1.8994169 | H18: 1 | I18: 1 | J18: {='Towers'!$G$5*G18*H18*I18} | K18: {=IF(J18=0,0,F18/J18)} | L18: 1 | M18: Railshot | O18: 1 | R18: 3 | BJ18: 2 | CI18: A | CJ18: Each bullet goes through 3 dinos
A19: Hunting Blind | B19: Hardliner | C19: damage | D19: 5 | E19: {=ROUND('Towers'!$C$5*POWER('Tuning'!$B$12,D19),0)} | F19: {=F18+E19} | G19: 1.9002302 | H19: 1 | I19: 1 | J19: {='Towers'!$G$5*G19*H19*I19} | K19: {=IF(J19=0,0,F19/J19)} | L19: 1 | M19: Hide Buster | O19: 2 | P19: 4 | CI19: A | CJ19: Hits armoured dinos and bosses 4 times as hard
A20: Longshot Perch | B20: Deadeye | C20: targets | D20: 1 | E20: {=ROUND('Towers'!$C$6*POWER('Tuning'!$B$12,D20),0)} | F20: {='Towers'!$C$6+E20} | G20: 1.45 | H20: 1 | I20: 1.32 | J20: {='Towers'!$G$6*G20*H20*I20} | K20: {=IF(J20=0,0,F20/J20)} | L20: 1 | M20: Full Metal Jacket | R20: 2
A21: Longshot Perch | B21: Deadeye | C21: targets | D21: 2 | E21: {=ROUND('Towers'!$C$6*POWER('Tuning'!$B$12,D21),0)} | F21: {=F20+E21} | G21: 2.1 | H21: 1 | I21: 1.74 | J21: {='Towers'!$G$6*G21*H21*I21} | K21: {=IF(J21=0,0,F21/J21)} | L21: 1 | M21: Through-and-Through | N21: Yes | R21: 3
A22: Longshot Perch | B22: Deadeye | C22: targets | D22: 3 | E22: {=ROUND('Towers'!$C$6*POWER('Tuning'!$B$12,D22),0)} | F22: {=F21+E22} | G22: 3.05 | H22: 1 | I22: 2.3 | J22: {='Towers'!$G$6*G22*H22*I22} | K22: {=IF(J22=0,0,F22/J22)} | L22: 1 | M22: Ricochet | N22: Yes | R22: 4
A23: Longshot Perch | B23: Deadeye | C23: targets | D23: 4 | E23: {=ROUND('Towers'!$C$6*POWER('Tuning'!$B$12,D23),0)} | F23: {=F22+E23} | G23: 1.4491803 | H23: 1 | I23: 1.3217391 | J23: {='Towers'!$G$6*G23*H23*I23} | K23: {=IF(J23=0,0,F23/J23)} | L23: 1 | M23: Tungsten Core | R23: 6 | BJ23: 2 | CI23: A | CJ23: Shots go through more dinos, shrinking each 2 sizes
A24: Longshot Perch | B24: Deadeye | C24: targets | D24: 5 | E24: {=ROUND('Towers'!$C$6*POWER('Tuning'!$B$12,D24),0)} | F24: {=F23+E24} | G24: 2 | H24: 1 | I24: 1.3190789 | J24: {='Towers'!$G$6*G24*H24*I24} | K24: {=IF(J24=0,0,F24/J24)} | L24: 1 | M24: Linebreaker | R24: 10 | BJ24: 3 | CI24: A | CJ24: Each shot hits 10 dinos in a line, double damage
A25: Longshot Perch | B25: Spotter | C25: rate | D25: 1 | E25: {=ROUND('Towers'!$C$6*POWER('Tuning'!$B$12,D25),0)} | F25: {='Towers'!$C$6+E25} | G25: 1.35 | H25: 1.42 | I25: 1 | J25: {='Towers'!$G$6*G25*H25*I25} | K25: {=IF(J25=0,0,F25/J25)} | L25: 1 | M25: Steady Breath
A26: Longshot Perch | B26: Spotter | C26: rate | D26: 2 | E26: {=ROUND('Towers'!$C$6*POWER('Tuning'!$B$12,D26),0)} | F26: {=F25+E26} | G26: 1.82 | H26: 2.02 | I26: 1 | J26: {='Towers'!$G$6*G26*H26*I26} | K26: {=IF(J26=0,0,F26/J26)} | L26: 1 | M26: Bolt Racking
A27: Longshot Perch | B27: Spotter | C27: rate | D27: 3 | E27: {=ROUND('Towers'!$C$6*POWER('Tuning'!$B$12,D27),0)} | F27: {=F26+E27} | G27: 2.46 | H27: 2.86 | I27: 1 | J27: {='Towers'!$G$6*G27*H27*I27} | K27: {=IF(J27=0,0,F27/J27)} | L27: 1 | M27: Marked Target | T27: 25
A28: Longshot Perch | B28: Spotter | C28: rate | D28: 4 | E28: {=ROUND('Towers'!$C$6*POWER('Tuning'!$B$12,D28),0)} | F28: {=F27+E28} | G28: 1.3495935 | H28: 1.4230769 | I28: 1 | J28: {='Towers'!$G$6*G28*H28*I28} | K28: {=IF(J28=0,0,F28/J28)} | L28: 1 | M28: Game Spotter | T28: 35 | CI28: A | CJ28: Fires faster, and its mark hits harder
A29: Longshot Perch | B29: Spotter | C29: rate | D29: 5 | E29: {=ROUND('Towers'!$C$6*POWER('Tuning'!$B$12,D29),0)} | F29: {=F28+E29} | G29: 1.3493976 | H29: 1.4176904 | I29: 1 | J29: {='Towers'!$G$6*G29*H29*I29} | K29: {=IF(J29=0,0,F29/J29)} | L29: 1 | M29: Eye in the Sky | T29: 60 | AB29: 15 | CI29: A | CJ29: A bigger mark, and towers in range shoot faster
A30: Longshot Perch | B30: Big Bore | C30: damage | D30: 1 | E30: {=ROUND('Towers'!$C$6*POWER('Tuning'!$B$12,D30),0)} | F30: {='Towers'!$C$6+E30} | G30: 1.9 | H30: 1 | I30: 1 | J30: {='Towers'!$G$6*G30*H30*I30} | K30: {=IF(J30=0,0,F30/J30)} | L30: 1 | M30: Large Calibre
A31: Longshot Perch | B31: Big Bore | C31: damage | D31: 2 | E31: {=ROUND('Towers'!$C$6*POWER('Tuning'!$B$12,D31),0)} | F31: {=F30+E31} | G31: 3.61 | H31: 1 | I31: 1 | J31: {='Towers'!$G$6*G31*H31*I31} | K31: {=IF(J31=0,0,F31/J31)} | L31: 1 | M31: Bone Breaker | P31: 3 | BJ31: 2
A32: Longshot Perch | B32: Big Bore | C32: damage | D32: 3 | E32: {=ROUND('Towers'!$C$6*POWER('Tuning'!$B$12,D32),0)} | F32: {=F31+E32} | G32: 6.86 | H32: 1 | I32: 1 | J32: {='Towers'!$G$6*G32*H32*I32} | K32: {=IF(J32=0,0,F32/J32)} | L32: 1 | M32: Concussion Round | P32: 3 | U32: 0.4 | BJ32: 2
A33: Longshot Perch | B33: Big Bore | C33: damage | D33: 4 | E33: {=ROUND('Towers'!$C$6*POWER('Tuning'!$B$12,D33),0)} | F33: {=F32+E33} | G33: 1.8994169 | H33: 1 | I33: 1 | J33: {='Towers'!$G$6*G33*H33*I33} | K33: {=IF(J33=0,0,F33/J33)} | L33: 1 | M33: Punt Gun | P33: 1.6666667 | U33: 0.5 | BJ33: 3 | CI33: A | CJ33: Huge shots that stun and shrink a dino 3 sizes
A34: Longshot Perch | B34: Big Bore | C34: damage | D34: 5 | E34: {=ROUND('Towers'!$C$6*POWER('Tuning'!$B$12,D34),0)} | F34: {=F33+E34} | G34: 1.9002302 | H34: 1 | I34: 1 | J34: {='Towers'!$G$6*G34*H34*I34} | K34: {=IF(J34=0,0,F34/J34)} | L34: 1 | M34: Extinction Round | P34: 2 | U34: 0.8 | V34: Yes | BJ34: 4 | CI34: A | CJ34: 10 times damage to bosses, and stuns them
A35: Mortar Pit | B35: Blast | C35: targets | D35: 1 | E35: {=ROUND('Towers'!$C$7*POWER('Tuning'!$B$12,D35),0)} | F35: {='Towers'!$C$7+E35} | G35: 1.45 | H35: 1 | I35: 1.32 | J35: {='Towers'!$G$7*G35*H35*I35} | K35: {=IF(J35=0,0,F35/J35)} | L35: 1 | M35: Bigger Bang | S35: 1.25
A36: Mortar Pit | B36: Blast | C36: targets | D36: 2 | E36: {=ROUND('Towers'!$C$7*POWER('Tuning'!$B$12,D36),0)} | F36: {=F35+E36} | G36: 2.1 | H36: 1 | I36: 1.74 | J36: {='Towers'!$G$7*G36*H36*I36} | K36: {=IF(J36=0,0,F36/J36)} | L36: 1 | M36: Shrapnel | S36: 1.4
A37: Mortar Pit | B37: Blast | C37: targets | D37: 3 | E37: {=ROUND('Towers'!$C$7*POWER('Tuning'!$B$12,D37),0)} | F37: {=F36+E37} | G37: 3.05 | H37: 1 | I37: 2.3 | J37: {='Towers'!$G$7*G37*H37*I37} | K37: {=IF(J37=0,0,F37/J37)} | L37: 1 | M37: Napalm | S37: 1.5 | X37: 1 | Y37: 3
A38: Mortar Pit | B38: Blast | C38: targets | D38: 4 | E38: {=ROUND('Towers'!$C$7*POWER('Tuning'!$B$12,D38),0)} | F38: {=F37+E38} | G38: 1.4491803 | H38: 1 | I38: 1.3217391 | J38: {='Towers'!$G$7*G38*H38*I38} | K38: {=IF(J38=0,0,F38/J38)} | L38: 1 | M38: Firestorm | S38: 1.0666667 | X38: 2 | Y38: 4 | CI38: A | CJ38: Bigger blasts that leave dinos burning
A39: Mortar Pit | B39: Blast | C39: targets | D39: 5 | E39: {=ROUND('Towers'!$C$7*POWER('Tuning'!$B$12,D39),0)} | F39: {=F38+E39} | G39: 1.4502262 | H39: 1 | I39: 1.3190789 | J39: {='Towers'!$G$7*G39*H39*I39} | K39: {=IF(J39=0,0,F39/J39)} | L39: 1 | M39: Scorched Earth | S39: 1.125 | X39: 4 | Y39: 6 | CI39: A | CJ39: Leaves a long burning stretch of track
A40: Mortar Pit | B40: Cluster | C40: targets | D40: 1 | E40: {=ROUND('Towers'!$C$7*POWER('Tuning'!$B$12,D40),0)} | F40: {='Towers'!$C$7+E40} | G40: 1.45 | H40: 1 | I40: 1.32 | J40: {='Towers'!$G$7*G40*H40*I40} | K40: {=IF(J40=0,0,F40/J40)} | L40: 1 | M40: Cluster Shell | Z40: 3 | AA40: 1
A41: Mortar Pit | B41: Cluster | C41: targets | D41: 2 | E41: {=ROUND('Towers'!$C$7*POWER('Tuning'!$B$12,D41),0)} | F41: {=F40+E41} | G41: 2.1 | H41: 1 | I41: 1.74 | J41: {='Towers'!$G$7*G41*H41*I41} | K41: {=IF(J41=0,0,F41/J41)} | L41: 1 | M41: Rapid Loader | Z41: 3 | AA41: 1
A42: Mortar Pit | B42: Cluster | C42: targets | D42: 3 | E42: {=ROUND('Towers'!$C$7*POWER('Tuning'!$B$12,D42),0)} | F42: {=F41+E42} | G42: 3.05 | H42: 1 | I42: 2.3 | J42: {='Towers'!$G$7*G42*H42*I42} | K42: {=IF(J42=0,0,F42/J42)} | L42: 1 | M42: Chain Reaction | Z42: 3 | AA42: 2
A43: Mortar Pit | B43: Cluster | C43: targets | D43: 4 | E43: {=ROUND('Towers'!$C$7*POWER('Tuning'!$B$12,D43),0)} | F43: {=F42+E43} | G43: 1.4491803 | H43: 1 | I43: 1.3217391 | J43: {='Towers'!$G$7*G43*H43*I43} | K43: {=IF(J43=0,0,F43/J43)} | L43: 1 | M43: Carpet Shelling | Z43: 4 | CI43: A | CJ43: More bomblets and harder blasts
A44: Mortar Pit | B44: Cluster | C44: targets | D44: 5 | E44: {=ROUND('Towers'!$C$7*POWER('Tuning'!$B$12,D44),0)} | F44: {=F43+E44} | G44: 1.4502262 | H44: 1 | I44: 1.3190789 | J44: {='Towers'!$G$7*G44*H44*I44} | K44: {=IF(J44=0,0,F44/J44)} | L44: 1 | M44: Meteor Shower | Z44: 5 | CI44: A | CJ44: Even more bomblets rain down
A45: Mortar Pit | B45: Concussive | C45: damage | D45: 1 | E45: {=ROUND('Towers'!$C$7*POWER('Tuning'!$B$12,D45),0)} | F45: {='Towers'!$C$7+E45} | G45: 1.9 | H45: 1 | I45: 1 | J45: {='Towers'!$G$7*G45*H45*I45} | K45: {=IF(J45=0,0,F45/J45)} | L45: 1 | M45: Shockwave | W45: 3
A46: Mortar Pit | B46: Concussive | C46: damage | D46: 2 | E46: {=ROUND('Towers'!$C$7*POWER('Tuning'!$B$12,D46),0)} | F46: {=F45+E46} | G46: 3.61 | H46: 1 | I46: 1 | J46: {='Towers'!$G$7*G46*H46*I46} | K46: {=IF(J46=0,0,F46/J46)} | L46: 1 | M46: Armor Crack | N46: Yes | O46: 2 | W46: 3
A47: Mortar Pit | B47: Concussive | C47: damage | D47: 3 | E47: {=ROUND('Towers'!$C$7*POWER('Tuning'!$B$12,D47),0)} | F47: {=F46+E47} | G47: 6.86 | H47: 1 | I47: 1 | J47: {='Towers'!$G$7*G47*H47*I47} | K47: {=IF(J47=0,0,F47/J47)} | L47: 1 | M47: Stun Grenade | N47: Yes | O47: 2 | U47: 0.3 | W47: 3
A48: Mortar Pit | B48: Concussive | C48: damage | D48: 4 | E48: {=ROUND('Towers'!$C$7*POWER('Tuning'!$B$12,D48),0)} | F48: {=F47+E48} | G48: 1.8994169 | H48: 1 | I48: 1 | J48: {='Towers'!$G$7*G48*H48*I48} | K48: {=IF(J48=0,0,F48/J48)} | L48: 1 | M48: Earthshaker | O48: 1 | W48: 6 | CI48: A | CJ48: Hits much harder and knocks dinos further back
A49: Mortar Pit | B49: Concussive | C49: damage | D49: 5 | E49: {=ROUND('Towers'!$C$7*POWER('Tuning'!$B$12,D49),0)} | F49: {=F48+E49} | G49: 2.609363 | H49: 1 | I49: 1 | J49: {='Towers'!$G$7*G49*H49*I49} | K49: {=IF(J49=0,0,F49/J49)} | L49: 1 | M49: Tectonic Slam | O49: 1 | U49: 1 | CI49: A | CJ49: Stuns every dino it hits for a second
A50: Tranq Station | B50: Sedate | C50: range | D50: 1 | E50: {=ROUND('Towers'!$C$8*POWER('Tuning'!$B$12,D50),0)} | F50: {='Towers'!$C$8+E50} | G50: 1.3 | H50: 1.15 | I50: 1 | J50: {='Towers'!$G$8*G50*H50*I50} | K50: {=IF(J50=0,0,F50/J50)} | L50: 1.15 | M50: Mild Dose | AE50: 50
A51: Tranq Station | B51: Sedate | C51: range | D51: 2 | E51: {=ROUND('Towers'!$C$8*POWER('Tuning'!$B$12,D51),0)} | F51: {=F50+E51} | G51: 1.69 | H51: 1.32 | I51: 1 | J51: {='Towers'!$G$8*G51*H51*I51} | K51: {=IF(J51=0,0,F51/J51)} | L51: 1.3 | M51: Heavy Dose | AE51: 60
A52: Tranq Station | B52: Sedate | C52: range | D52: 3 | E52: {=ROUND('Towers'!$C$8*POWER('Tuning'!$B$12,D52),0)} | F52: {=F51+E52} | G52: 2.2 | H52: 1.52 | I52: 1 | J52: {='Towers'!$G$8*G52*H52*I52} | K52: {=IF(J52=0,0,F52/J52)} | L52: 1.5 | M52: Lingering Dose | AE52: 60 | AF52: 2
A53: Tranq Station | B53: Sedate | C53: range | D53: 4 | E53: {=ROUND('Towers'!$C$8*POWER('Tuning'!$B$12,D53),0)} | F53: {=F52+E53} | G53: 1.3 | H53: 1.1513158 | I53: 1 | J53: {='Towers'!$G$8*G53*H53*I53} | K53: {=IF(J53=0,0,F53/J53)} | L53: 1.1666667 | M53: Sedative Cloud | AE53: 70 | CI53: A | CJ53: A much stronger slow over a wider area
A54: Tranq Station | B54: Sedate | C54: range | D54: 5 | E54: {=ROUND('Towers'!$C$8*POWER('Tuning'!$B$12,D54),0)} | F54: {=F53+E54} | G54: 1.2972028 | H54: 1.1485714 | I54: 1 | J54: {='Towers'!$G$8*G54*H54*I54} | K54: {=IF(J54=0,0,F54/J54)} | L54: 1.1428571 | M54: Deep Sleep | AE54: 80 | AF54: 3 | AG54: Yes | CI54: A | CJ54: Its slow works on bosses too
A55: Tranq Station | B55: Knockout | C55: rate | D55: 1 | E55: {=ROUND('Towers'!$C$8*POWER('Tuning'!$B$12,D55),0)} | F55: {='Towers'!$C$8+E55} | G55: 1.35 | H55: 1.42 | I55: 1 | J55: {='Towers'!$G$8*G55*H55*I55} | K55: {=IF(J55=0,0,F55/J55)} | L55: 1 | M55: Knockout Dart | AH55: 8 | AI55: 0.6
A56: Tranq Station | B56: Knockout | C56: rate | D56: 2 | E56: {=ROUND('Towers'!$C$8*POWER('Tuning'!$B$12,D56),0)} | F56: {=F55+E56} | G56: 1.82 | H56: 2.02 | I56: 1 | J56: {='Towers'!$G$8*G56*H56*I56} | K56: {=IF(J56=0,0,F56/J56)} | L56: 1 | M56: Heavy Sedative | AH56: 8 | AI56: 1
A57: Tranq Station | B57: Knockout | C57: rate | D57: 3 | E57: {=ROUND('Towers'!$C$8*POWER('Tuning'!$B$12,D57),0)} | F57: {=F56+E57} | G57: 2.46 | H57: 2.86 | I57: 1 | J57: {='Towers'!$G$8*G57*H57*I57} | K57: {=IF(J57=0,0,F57/J57)} | L57: 1 | M57: Barbed Darts | AH57: 7 | AI57: 1 | AJ57: 2
A58: Tranq Station | B58: Knockout | C58: rate | D58: 4 | E58: {=ROUND('Towers'!$C$8*POWER('Tuning'!$B$12,D58),0)} | F58: {=F57+E58} | G58: 1.3495935 | H58: 1.4230769 | I58: 1 | J58: {='Towers'!$G$8*G58*H58*I58} | K58: {=IF(J58=0,0,F58/J58)} | L58: 1 | M58: Quick Cycle | AH58: 5 | AJ58: 3 | CI58: A | CJ58: Knockouts come sooner and hurt more
A59: Tranq Station | B59: Knockout | C59: rate | D59: 5 | E59: {=ROUND('Towers'!$C$8*POWER('Tuning'!$B$12,D59),0)} | F59: {=F58+E59} | G59: 1.3493976 | H59: 1.4176904 | I59: 1 | J59: {='Towers'!$G$8*G59*H59*I59} | K59: {=IF(J59=0,0,F59/J59)} | L59: 1 | M59: Big Game Tranq | AI59: 2 | AJ59: 5 | AK59: Yes | CI59: A | CJ59: A long knockout that even holds bosses
A60: Tranq Station | B60: Weak Spot | C60: damage | D60: 1 | E60: {=ROUND('Towers'!$C$8*POWER('Tuning'!$B$12,D60),0)} | F60: {='Towers'!$C$8+E60} | G60: 1.9 | H60: 1 | I60: 1 | J60: {='Towers'!$G$8*G60*H60*I60} | K60: {=IF(J60=0,0,F60/J60)} | L60: 1 | M60: Exposed Hide | AL60: 25
A61: Tranq Station | B61: Weak Spot | C61: damage | D61: 2 | E61: {=ROUND('Towers'!$C$8*POWER('Tuning'!$B$12,D61),0)} | F61: {=F60+E61} | G61: 3.61 | H61: 1 | I61: 1 | J61: {='Towers'!$G$8*G61*H61*I61} | K61: {=IF(J61=0,0,F61/J61)} | L61: 1 | M61: Find the Gap | AL61: 35 | AM61: Yes
A62: Tranq Station | B62: Weak Spot | C62: damage | D62: 3 | E62: {=ROUND('Towers'!$C$8*POWER('Tuning'!$B$12,D62),0)} | F62: {=F61+E62} | G62: 6.86 | H62: 1 | I62: 1 | J62: {='Towers'!$G$8*G62*H62*I62} | K62: {=IF(J62=0,0,F62/J62)} | L62: 1 | M62: Hunter's Call | AB62: 10 | AL62: 35 | AM62: Yes
A63: Tranq Station | B63: Weak Spot | C63: damage | D63: 4 | E63: {=ROUND('Towers'!$C$8*POWER('Tuning'!$B$12,D63),0)} | F63: {=F62+E63} | G63: 1.8994169 | H63: 1 | I63: 1 | J63: {='Towers'!$G$8*G63*H63*I63} | K63: {=IF(J63=0,0,F63/J63)} | L63: 1 | M63: Vital Points | AL63: 50 | CI63: A | CJ63: Sedated dinos take even more damage
A64: Tranq Station | B64: Weak Spot | C64: damage | D64: 5 | E64: {=ROUND('Towers'!$C$8*POWER('Tuning'!$B$12,D64),0)} | F64: {=F63+E64} | G64: 1.9002302 | H64: 1 | I64: 1 | J64: {='Towers'!$G$8*G64*H64*I64} | K64: {=IF(J64=0,0,F64/J64)} | L64: 1 | M64: Apex Predator | AC64: 20 | AL64: 75 | CI64: A | CJ64: Dinos take much more damage; towers in range hit harder
A65: Supply Camp | B65: Yield | C65: economy | D65: 1 | E65: {=ROUND('Towers'!$C$9*POWER('Towers'!$S$9,D65),0)} | F65: {='Towers'!$C$9+E65} | G65: 1 | H65: 1 | I65: 1 | J65: 0 | K65: n/a | L65: 1 | M65: Supply Crate | AN65: 2.1
A66: Supply Camp | B66: Yield | C66: economy | D66: 2 | E66: {=ROUND('Towers'!$C$9*POWER('Towers'!$S$9,D66),0)} | F66: {=F65+E66} | G66: 1 | H66: 1 | I66: 1 | J66: 0 | K66: n/a | L66: 1 | M66: Bigger Budget | AN66: 3.85
A67: Supply Camp | B67: Yield | C67: economy | D67: 3 | E67: {=ROUND('Towers'!$C$9*POWER('Towers'!$S$9,D67),0)} | F67: {=F66+E67} | G67: 1 | H67: 1 | I67: 1 | J67: 0 | K67: n/a | L67: 1 | M67: Trade Route | AN67: 6.6
A68: Supply Camp | B68: Yield | C68: economy | D68: 4 | E68: {=ROUND('Towers'!$C$9*POWER('Towers'!$S$9,D68),0)} | F68: {=F67+E68} | G68: 1 | H68: 1 | I68: 1 | J68: 0 | K68: n/a | L68: 1 | M68: War Chest | AN68: 1.6818182 | CI68: A | CJ68: Pays a lot more cash every round
A69: Supply Camp | B69: Yield | C69: economy | D69: 5 | E69: {=ROUND('Towers'!$C$9*POWER('Towers'!$S$9,D69),0)} | F69: {=F68+E69} | G69: 1 | H69: 1 | I69: 1 | J69: 0 | K69: n/a | L69: 1 | M69: Amber Vault | AN69: 1.6126126 | AO69: 5 | AP69: 500 | CI69: A | CJ69: Earns interest on your banked cash
A70: Supply Camp | B70: Airdrop | C70: economy | D70: 1 | E70: {=ROUND('Towers'!$C$9*POWER('Towers'!$S$9,D70),0)} | F70: {='Towers'!$C$9+E70} | G70: 1 | H70: 1 | I70: 1 | J70: 0 | K70: n/a | L70: 1 | M70: Air Drop | AQ70: 1 | AR70: 200
A71: Supply Camp | B71: Airdrop | C71: economy | D71: 2 | E71: {=ROUND('Towers'!$C$9*POWER('Towers'!$S$9,D71),0)} | F71: {=F70+E71} | G71: 1 | H71: 1 | I71: 1 | J71: 0 | K71: n/a | L71: 1 | M71: Double Drop | AQ71: 2 | AR71: 260
A72: Supply Camp | B72: Airdrop | C72: economy | D72: 3 | E72: {=ROUND('Towers'!$C$9*POWER('Towers'!$S$9,D72),0)} | F72: {=F71+E72} | G72: 1 | H72: 1 | I72: 1 | J72: 0 | K72: n/a | L72: 1 | M72: Chopper Drop | AQ72: 2 | AR72: 515
A73: Supply Camp | B73: Airdrop | C73: economy | D73: 4 | E73: {=ROUND('Towers'!$C$9*POWER('Towers'!$S$9,D73),0)} | F73: {=F72+E73} | G73: 1 | H73: 1 | I73: 1 | J73: 0 | K73: n/a | L73: 1 | M73: Supply Chain | AQ73: 3 | AR73: 615 | CI73: A | CJ73: More chests land each round, worth more
A74: Supply Camp | B74: Airdrop | C74: economy | D74: 5 | E74: {=ROUND('Towers'!$C$9*POWER('Towers'!$S$9,D74),0)} | F74: {=F73+E74} | G74: 1 | H74: 1 | I74: 1 | J74: 0 | K74: n/a | L74: 1 | M74: Treasure Haul | AQ74: 4 | AR74: 790 | CI74: A | CJ74: The richest chests, and more of them
A75: Supply Camp | B75: Logistics | C75: economy | D75: 1 | E75: {=ROUND('Towers'!$C$9*POWER('Towers'!$S$9,D75),0)} | F75: {='Towers'!$C$9+E75} | G75: 1 | H75: 1 | I75: 1 | J75: 0 | K75: n/a | L75: 1 | M75: Bulk Order | AS75: 5
A76: Supply Camp | B76: Logistics | C76: economy | D76: 2 | E76: {=ROUND('Towers'!$C$9*POWER('Towers'!$S$9,D76),0)} | F76: {=F75+E76} | G76: 1 | H76: 1 | I76: 1 | J76: 0 | K76: n/a | L76: 1 | M76: Field Engineer | AS76: 10
A77: Supply Camp | B77: Logistics | C77: economy | D77: 3 | E77: {=ROUND('Towers'!$C$9*POWER('Towers'!$S$9,D77),0)} | F77: {=F76+E77} | G77: 1 | H77: 1 | I77: 1 | J77: 0 | K77: n/a | L77: 1 | M77: Recycler | AS77: 10 | AT77: 0.9
A78: Supply Camp | B78: Logistics | C78: economy | D78: 4 | E78: {=ROUND('Towers'!$C$9*POWER('Towers'!$S$9,D78),0)} | F78: {=F77+E78} | G78: 1 | H78: 1 | I78: 1 | J78: 0 | K78: n/a | L78: 1 | M78: Forward Camp | AB78: 10 | CI78: A | CJ78: Towers in range shoot faster
A79: Supply Camp | B79: Logistics | C79: economy | D79: 5 | E79: {=ROUND('Towers'!$C$9*POWER('Towers'!$S$9,D79),0)} | F79: {=F78+E79} | G79: 1 | H79: 1 | I79: 1 | J79: 0 | K79: n/a | L79: 1 | M79: Base Camp | AS79: 20 | AT79: 1 | CI79: A | CJ79: Towers in range cost less and sell for full price
A80: Armory | B80: Plating | C80: resistance | D80: 1 | E80: =ROUND('Towers'!$C$11*POWER('Tuning'!$B$12,D80),0) | F80: ='Towers'!$C$11+E80 | G80: 1 | H80: 1 | I80: 1 | J80: 0 | K80: n/a | L80: 1 | M80: Hide Padding | AU80: 20
A81: Armory | B81: Plating | C81: resistance | D81: 2 | E81: =ROUND('Towers'!$C$11*POWER('Tuning'!$B$12,D81),0) | F81: =F80+E81 | G81: 1 | H81: 1 | I81: 1 | J81: 0 | K81: n/a | L81: 1 | M81: Iron Plates | AU81: 25
A82: Armory | B82: Plating | C82: resistance | D82: 3 | E82: =ROUND('Towers'!$C$11*POWER('Tuning'!$B$12,D82),0) | F82: =F81+E82 | G82: 1 | H82: 1 | I82: 1 | J82: 0 | K82: n/a | L82: 1 | M82: Thorn Plating | AU82: 25 | AV82: 3
A83: Armory | B83: Plating | C83: resistance | D83: 4 | E83: =ROUND('Towers'!$C$11*POWER('Tuning'!$B$12,D83),0) | F83: =F82+E83 | G83: 1 | H83: 1 | I83: 1 | J83: 0 | K83: n/a | L83: 1 | M83: Tempered Steel | AU83: 35 | AV83: 5 | CI83: A | CJ83: Tougher armour, and biters take more damage back
A84: Armory | B84: Plating | C84: resistance | D84: 5 | E84: =ROUND('Towers'!$C$11*POWER('Tuning'!$B$12,D84),0) | F84: =F83+E84 | G84: 1 | H84: 1 | I84: 1 | J84: 0 | K84: n/a | L84: 1 | M84: Bulwark | AU84: 45 | AW84: 0.5 | CI84: A | CJ84: The best armour; biting dinos get stunned (not bosses)
A85: Armory | B85: Gunsmith | C85: support | D85: 1 | E85: =ROUND('Towers'!$C$11*POWER('Tuning'!$B$12,D85),0) | F85: ='Towers'!$C$11+E85 | G85: 1 | H85: 1 | I85: 1 | J85: 0 | K85: n/a | L85: 1 | M85: Oiled Actions | AB85: 5
A86: Armory | B86: Gunsmith | C86: support | D86: 2 | E86: =ROUND('Towers'!$C$11*POWER('Tuning'!$B$12,D86),0) | F86: =F85+E86 | G86: 1 | H86: 1 | I86: 1 | J86: 0 | K86: n/a | L86: 1 | M86: Hand Loads | AB86: 5 | AC86: 10
A87: Armory | B87: Gunsmith | C87: support | D87: 3 | E87: =ROUND('Towers'!$C$11*POWER('Tuning'!$B$12,D87),0) | F87: =F86+E87 | G87: 1 | H87: 1 | I87: 1 | J87: 0 | K87: n/a | L87: 1 | M87: Piercing Rounds | AB87: 5 | AC87: 10 | AD87: Yes
A88: Armory | B88: Gunsmith | C88: support | D88: 4 | E88: =ROUND('Towers'!$C$11*POWER('Tuning'!$B$12,D88),0) | F88: =F87+E88 | G88: 1 | H88: 1 | I88: 1 | J88: 0 | K88: n/a | L88: 1 | M88: Match Grade | AB88: 10 | AC88: 20 | CI88: A | CJ88: Towers in range hit harder and shoot faster
A89: Armory | B89: Gunsmith | C89: support | D89: 5 | E89: =ROUND('Towers'!$C$11*POWER('Tuning'!$B$12,D89),0) | F89: =F88+E89 | G89: 1 | H89: 1 | I89: 1 | J89: 0 | K89: n/a | L89: 1 | M89: Master Gunsmith | AB89: 15 | AC89: 30 | CI89: A | CJ89: Towers in range hit much harder and faster
A90: Armory | B90: Outfitter | C90: hunters | D90: 1 | E90: =ROUND('Towers'!$C$11*POWER('Tuning'!$B$12,D90),0) | F90: ='Towers'!$C$11+E90 | G90: 1 | H90: 1 | I90: 1 | J90: 0 | K90: n/a | L90: 1.3 | M90: Wide Rack
A91: Armory | B91: Outfitter | C91: hunters | D91: 2 | E91: =ROUND('Towers'!$C$11*POWER('Tuning'!$B$12,D91),0) | F91: =F90+E91 | G91: 1 | H91: 1 | I91: 1 | J91: 0 | K91: n/a | L91: 1.3 | M91: Recoil Pads | AX91: 0.75
A92: Armory | B92: Outfitter | C92: hunters | D92: 3 | E92: =ROUND('Towers'!$C$11*POWER('Tuning'!$B$12,D92),0) | F92: =F91+E92 | G92: 1 | H92: 1 | I92: 1 | J92: 0 | K92: n/a | L92: 1.3 | M92: Ammo Crate | AX92: 0.75 | AY92: 0.65
A93: Armory | B93: Outfitter | C93: hunters | D93: 4 | E93: =ROUND('Towers'!$C$11*POWER('Tuning'!$B$12,D93),0) | F93: =F92+E93 | G93: 1 | H93: 1 | I93: 1 | J93: 0 | K93: n/a | L93: 1 | M93: Steady Rests | AX93: 1 | AY93: 1 | AZ93: 0.7 | CI93: A | CJ93: Hunters in range shoot straighter
A94: Armory | B94: Outfitter | C94: hunters | D94: 5 | E94: =ROUND('Towers'!$C$11*POWER('Tuning'!$B$12,D94),0) | F94: =F93+E94 | G94: 1 | H94: 1 | I94: 1 | J94: 0 | K94: n/a | L94: 1.1538462 | M94: Full Kit | AX94: 1 | AY94: 1 | AZ94: 1 | BA94: 20 | CI94: A | CJ94: Wider reach, and hunters in range fire faster
A95: Field Hospital | B95: Ward | C95: healing | D95: 1 | E95: =ROUND('Towers'!$C$10*POWER('Tuning'!$B$12,D95),0) | F95: ='Towers'!$C$10+E95 | G95: 1 | H95: 1 | I95: 1 | J95: 0 | K95: n/a | L95: 1 | M95: Clean Linens | BB95: 1.5
A96: Field Hospital | B96: Ward | C96: healing | D96: 2 | E96: =ROUND('Towers'!$C$10*POWER('Tuning'!$B$12,D96),0) | F96: =F95+E96 | G96: 1 | H96: 1 | I96: 1 | J96: 0 | K96: n/a | L96: 1 | M96: Extra Cots | BB96: 2
A97: Field Hospital | B97: Ward | C97: healing | D97: 3 | E97: =ROUND('Towers'!$C$10*POWER('Tuning'!$B$12,D97),0) | F97: =F96+E97 | G97: 1 | H97: 1 | I97: 1 | J97: 0 | K97: n/a | L97: 1 | M97: Stitch-Up | BB97: 2.5 | BC97: Yes | BD97: 0.5
A98: Field Hospital | B98: Ward | C98: healing | D98: 4 | E98: =ROUND('Towers'!$C$10*POWER('Tuning'!$B$12,D98),0) | F98: =F97+E98 | G98: 1 | H98: 1 | I98: 1 | J98: 0 | K98: n/a | L98: 1 | M98: Night Shift | BB98: 1.2 | CI98: A | CJ98: Heals towers and hunters even faster
A99: Field Hospital | B99: Ward | C99: healing | D99: 5 | E99: =ROUND('Towers'!$C$10*POWER('Tuning'!$B$12,D99),0) | F99: =F98+E99 | G99: 1 | H99: 1 | I99: 1 | J99: 0 | K99: n/a | L99: 1 | M99: Miracle Ward | BB99: 1.5 | BD99: 1 | CI99: A | CJ99: The fastest heals; trampled towers revive at full speed
A100: Field Hospital | B100: Rescue | C100: hunters | D100: 1 | E100: =ROUND('Towers'!$C$10*POWER('Tuning'!$B$12,D100),0) | F100: ='Towers'!$C$10+E100 | G100: 1 | H100: 1 | I100: 1 | J100: 0 | K100: n/a | L100: 1.2 | M100: Stretcher Team
A101: Field Hospital | B101: Rescue | C101: hunters | D101: 2 | E101: =ROUND('Towers'!$C$10*POWER('Tuning'!$B$12,D101),0) | F101: =F100+E101 | G101: 1 | H101: 1 | I101: 1 | J101: 0 | K101: n/a | L101: 1.4 | M101: Signal Whistle
...

Sheet Heroes
A1: HEROES — hunter classes, free to pick once owned; each is a weapon plus an ability (HEROES.md)
A2: Base gun before any upgrade. Hero Upgrades multiplies or overrides these. More heroes = more rows.
A4: Key | B4: Hero | C4: Role | D4: Ability | E4: Damage | F4: Fire rate /s | G4: Fire mode | H4: Magazine | I4: Reload (s) | J4: Pellets | K4: Spread (deg) | L4: Recoil per shot (deg) | M4: Recoil max (deg) | N4: Recoil recovery (deg/s) | O4: Range (m) | P4: Pierces armour | Q4: Hits air | R4: Splash radius (m) | S4: Ability power | T4: Ability (s) | U4: Ability radius (m) | V4: Ability cooldown (s) | W4: Note | X4: Unlock cost (amber) | Y4: Weapon | Z4: Ability kind
A5: PISTOL | B5: Tracker | C5: Precision | D5: Tracking Dart | E5: 1.5 | F5: 4 | G5: semi | H5: 12 | I5: 1.2 | J5: 1 | K5: 0.5 | L5: 1.2 | M5: 6 | N5: 12 | O5: 55 | P5: No | Q5: Yes | R5: 0 | S5: 50 | T5: 8 | U5: 0 | V5: 45 | W5: Mark: power = +% damage taken, (s) = length. Passes to splits. | X5: 0 | Y5: Revolver | Z5: MARK
A6: RIFLE | B6: Big Game Hunter | C6: Sustained | D6: Rally Cry | E6: 0.8 | F6: 8 | G6: auto | H6: 30 | I6: 2 | J6: 1 | K6: 1 | L6: 0.6 | M6: 8 | N6: 10 | O6: 40 | P6: No | Q6: Yes | R6: 0 | S6: 40 | T6: 10 | U6: 25 | V6: 45 | W6: Overdrive: your fire rate x Tuning, towers in radius +power% fire rate. | X6: 75 | Y6: Hunting Rifle | Z6: OVERDRIVE
A7: SHOTGUN | B7: Brush Beater | C7: Close range | D7: Flare Strike | E7: 0.8 | F7: 1.2 | G7: semi | H7: 6 | I7: 2.2 | J7: 6 | K7: 7 | L7: 3 | M7: 8 | N7: 8 | O7: 25 | P7: No | Q7: No | R7: 0 | S7: 30 | T7: 2 | U7: 10 | V7: 45 | W7: Airburst: power = damage, (s) = stun, radius on the track. | X7: 75 | Y7: Shotgun | Z7: AIRBURST
A8: MEDIC | B8: Field Medic | C8: Support | D8: Triage Kit | E8: 1 | F8: 3 | G8: semi | H8: 10 | I8: 1.8 | J8: 1 | K8: 0.8 | L8: 1 | M8: 6 | N8: 12 | O8: 45 | P8: No | Q8: Yes | R8: 0 | S8: 40 | T8: 0 | U8: 20 | V8: 35 | W8: Heal: power = HP healed (flat, not scaled by hero levels) to you and every hunter within radius. Triage adds tower repair (Patch Up) and Second Wind guard. | X8: 75 | Y8: Lever-Action Carbine | Z8: HEAL

Sheet Hero Upgrades
A1: HERO UPGRADES — 4 heroes x 3 paths x 6 tiers (HEROES.md)
A2: Effect columns are cumulative per tier (like Tower Upgrades); blank = no change. x columns multiply the hero's base; Fire mode / Guns / Pellets / Pierce / Bounces override it. Crossover rule as towers: two paths, one past tier 2. Damage is per shot: pellets share the hero's base damage x its base pellet count, so more pellets spread the same damage wider and a slug concentrates it. Ignite: an enemy hit burns for Ignite (s), then takes one tick of Ignite tick x the whole shot's damage. The fire passes to the enemy's split children, so a Brute shot down to Husks sees them burn out together. A/B/C (PLAN Phase 9, DECISIONS #275): tiers 1-3 rows are cumulative; a tier-4 or tier-5 row is one option (Option A/B/C, Blurb = its card line, max 60 chars) and holds ONLY ITS OWN STEP over the tier below; so does tier 6 (no option) (x columns multiply, amounts take the higher, flags add, overrides replace; blank = no change). The exporter composes every build. New options are appended at the bottom.
A4: Hero | B4: Path | C4: Focus | D4: Tier | E4: Name | F4: Cost | G4: Fire rate x | H4: Magazine x | I4: Reload x | J4: Spread x | K4: Recoil x | L4: Range x | M4: Damage x | N4: Fire mode | O4: Burst count | P4: Guns | Q4: Pellets | R4: Shots per trigger | S4: Pierce | T4: Bounces | U4: Pierces armour | V4: Hits air | W4: Burn DPS | X4: Burn (s) | Y4: Splash radius (m) | Z4: Knockback (studs) | AA4: Mark % | AB4: Marked damage x | AC4: Ability cooldown x | AD4: Belt fed | AE4: Still recoil x | AF4: Spin-up x | AG4: Scope | AH4: Ignite (s) | AI4: Ignite tick (x shot) | AJ4: Heal x | AK4: Heal radius x | AL4: Heal repairs towers | AM4: Guard % | AN4: Guard (s) | AO4: Slow on hit % | AP4: Slow on hit (s) | AQ4: Jaw lock (s) | AR4: Jaw lock spread (studs) | AS4: Size breaks | AT4: Burn patch reach (studs) | AU4: Staggered reload | AV4: Ricochet reload (rounds) | AW4: Burst recoil reset | AX4: Spun-up belt | AY4: Still spread x | AZ4: Scoped spread x | BA4: Ability charges | BB4: Option | BC4: Blurb | BD4: Heal regen HP/s | BE4: Heal regen (s) | BF4: One round per trigger
A5: Tracker | B5: Gunslinger | C5: handling | D5: 1 | E5: Quick Draw | F5: =ROUND(Tuning!$B$21*POWER(Tuning!$B$22,D5-1),0) | G5: 1.15 | I5: 0.9
A6: Tracker | B6: Gunslinger | C6: handling | D6: 2 | E6: Hair Trigger | F6: =ROUND(Tuning!$B$21*POWER(Tuning!$B$22,D6-1),0) | G6: 1.3 | I6: 0.85
A7: Tracker | B7: Gunslinger | C7: handling | D7: 3 | E7: Dual Pistols | F7: =ROUND(Tuning!$B$21*POWER(Tuning!$B$22,D7-1),0) | G7: 1.3 | I7: 0.85 | P7: 2
A8: Tracker | B8: Gunslinger | C8: handling | D8: 4 | E8: Fan the Hammer | F8: =ROUND(Tuning!$B$21*POWER(Tuning!$B$22,D8-1),0) | G8: 1.2307692 | I8: 0.94117647 | BB8: A | BC8: Fires faster and reloads quicker
A9: Tracker | B9: Gunslinger | C9: handling | D9: 5 | E9: Akimbo Frenzy | F9: =ROUND(Tuning!$B$21*POWER(Tuning!$B$22,D9-1),0) | G9: 1.25 | H9: 1.5 | I9: 0.875 | N9: auto | BB9: A | BC9: Both guns go full-auto
A10: Tracker | B10: Marksman | C10: accuracy | D10: 1 | E10: Match Barrel | F10: =ROUND(Tuning!$B$21*POWER(Tuning!$B$22,D10-1),0) | J10: 0.6
A11: Tracker | B11: Marksman | C11: accuracy | D11: 2 | E11: Steady Hands | F11: =ROUND(Tuning!$B$21*POWER(Tuning!$B$22,D11-1),0) | J11: 0.5 | K11: 0.6
A12: Tracker | B12: Marksman | C12: accuracy | D12: 3 | E12: Scope | F12: =ROUND(Tuning!$B$21*POWER(Tuning!$B$22,D12-1),0) | J12: 0.3 | K12: 0.5 | L12: 1.6 | AG12: Yes
A13: Tracker | B13: Marksman | C13: accuracy | D13: 4 | E13: Hollow Tips | F13: =ROUND(Tuning!$B$21*POWER(Tuning!$B$22,D13-1),0) | J13: 1 | K13: 1 | L13: 1 | U13: Yes | BB13: A | BC13: Shots pierce armour
A14: Tracker | B14: Marksman | C14: accuracy | D14: 5 | E14: Deadshot | F14: =ROUND(Tuning!$B$21*POWER(Tuning!$B$22,D14-1),0) | J14: 0.83333333 | K14: 0.8 | L14: 1.125 | AB14: 3 | BB14: A | BC14: Triple damage to marked dinos
A15: Tracker | B15: Trick Shot | C15: utility | D15: 1 | E15: Speed Loader | F15: =ROUND(Tuning!$B$21*POWER(Tuning!$B$22,D15-1),0) | I15: 0.6
A16: Tracker | B16: Trick Shot | C16: utility | D16: 2 | E16: Extended Mag | F16: =ROUND(Tuning!$B$21*POWER(Tuning!$B$22,D16-1),0) | H16: 1.6 | I16: 0.6
A17: Tracker | B17: Trick Shot | C17: utility | D17: 3 | E17: Ricochet | F17: =ROUND(Tuning!$B$21*POWER(Tuning!$B$22,D17-1),0) | H17: 1.6 | I17: 0.6 | T17: 1
A18: Tracker | B18: Trick Shot | C18: utility | D18: 4 | E18: Quick Dart | F18: =ROUND(Tuning!$B$21*POWER(Tuning!$B$22,D18-1),0) | H18: 1 | I18: 1 | AC18: 0.6 | BB18: A | BC18: Your Tracking Dart is ready again sooner
A19: Tracker | B19: Trick Shot | C19: utility | D19: 5 | E19: Chain Shot | F19: =ROUND(Tuning!$B$21*POWER(Tuning!$B$22,D19-1),0) | H19: 1 | I19: 1 | T19: 4 | AC19: 1 | BB19: A | BC19: Shots bounce 4 times
A20: Big Game Hunter | B20: Stalker | C20: control | D20: 1 | E20: Foregrip | F20: =ROUND(Tuning!$B$21*POWER(Tuning!$B$22,D20-1),0) | K20: 0.75
A21: Big Game Hunter | B21: Stalker | C21: control | D21: 2 | E21: Compensator | F21: =ROUND(Tuning!$B$21*POWER(Tuning!$B$22,D21-1),0) | J21: 0.8 | K21: 0.55
A22: Big Game Hunter | B22: Stalker | C22: control | D22: 3 | E22: Burst Fire | F22: =ROUND(Tuning!$B$21*POWER(Tuning!$B$22,D22-1),0) | G22: 1.4 | J22: 0.6 | K22: 0.4 | N22: burst | O22: 3
A23: Big Game Hunter | B23: Stalker | C23: control | D23: 4 | E23: Trigger Discipline | F23: =ROUND(Tuning!$B$21*POWER(Tuning!$B$22,D23-1),0) | G23: 1 | J23: 1 | K23: 0.75 | L23: 1.3 | BB23: A | BC23: Less kick and longer reach
A24: Big Game Hunter | B24: Stalker | C24: control | D24: 5 | E24: Precision Burst | F24: =ROUND(Tuning!$B$21*POWER(Tuning!$B$22,D24-1),0) | G24: 1.0714286 | J24: 0.5 | K24: 0.83333333 | L24: 1.1538462 | M24: 1.3 | O24: 4 | BB24: A | BC24: 4-round bursts with a much tighter grouping
A25: Big Game Hunter | B25: Heavy | C25: sustain | D25: 1 | E25: Drum Mag | F25: =ROUND(Tuning!$B$21*POWER(Tuning!$B$22,D25-1),0) | H25: 1.7
A26: Big Game Hunter | B26: Heavy | C26: sustain | D26: 2 | E26: Fast Hands | F26: =ROUND(Tuning!$B$21*POWER(Tuning!$B$22,D26-1),0) | H26: 1.7 | I26: 0.65
A27: Big Game Hunter | B27: Heavy | C27: sustain | D27: 3 | E27: Belt Fed | F27: =ROUND(Tuning!$B$21*POWER(Tuning!$B$22,D27-1),0) | H27: 1.7 | I27: 0.65 | AD27: Yes
A28: Big Game Hunter | B28: Heavy | C28: sustain | D28: 4 | E28: Bipod | F28: =ROUND(Tuning!$B$21*POWER(Tuning!$B$22,D28-1),0) | H28: 1 | I28: 1 | AE28: 0.3 | BB28: A | BC28: Much less kick while you stand still
A29: Big Game Hunter | B29: Heavy | C29: sustain | D29: 5 | E29: Spin-Up | F29: =ROUND(Tuning!$B$21*POWER(Tuning!$B$22,D29-1),0) | H29: 1.2941176 | I29: 1 | AE29: 1 | AF29: 2.5 | BB29: A | BC29: Fire rate climbs while you hold the trigger
A30: Big Game Hunter | B30: Special Ammo | C30: rounds | D30: 1 | E30: Tracer Rounds | F30: =ROUND(Tuning!$B$21*POWER(Tuning!$B$22,D30-1),0) | AA30: 10
A31: Big Game Hunter | B31: Special Ammo | C31: rounds | D31: 2 | E31: Incendiary | F31: =ROUND(Tuning!$B$21*POWER(Tuning!$B$22,D31-1),0) | W31: 1 | X31: 2 | AA31: 10
A32: Big Game Hunter | B32: Special Ammo | C32: rounds | D32: 3 | E32: AP Rounds | F32: =ROUND(Tuning!$B$21*POWER(Tuning!$B$22,D32-1),0) | U32: Yes | W32: 1 | X32: 2 | AA32: 10
A33: Big Game Hunter | B33: Special Ammo | C33: rounds | D33: 4 | E33: Hot Load | F33: =ROUND(Tuning!$B$21*POWER(Tuning!$B$22,D33-1),0) | L33: 1.2 | M33: 1.25 | BB33: A | BC33: Hits harder and reaches further
A34: Big Game Hunter | B34: Special Ammo | C34: rounds | D34: 5 | E34: Explosive Tips | F34: =ROUND(Tuning!$B$21*POWER(Tuning!$B$22,D34-1),0) | L34: 1 | M34: 1 | Y34: 4 | BB34: A | BC34: Shots burst with a small splash
A35: Brush Beater | B35: Slug | C35: reach | D35: 1 | E35: Slug Rounds | F35: =ROUND(Tuning!$B$21*POWER(Tuning!$B$22,D35-1),0) | J35: 0.1 | L35: 1.8 | M35: 0.67 | Q35: 1 | S35: 2
A36: Brush Beater | B36: Slug | C36: reach | D36: 2 | E36: Rifled Barrel | F36: =ROUND(Tuning!$B$21*POWER(Tuning!$B$22,D36-1),0) | J36: 0.1 | L36: 2.2 | M36: 0.67 | Q36: 1 | S36: 2 | V36: Yes
A37: Brush Beater | B37: Slug | C37: reach | D37: 3 | E37: Sabot | F37: =ROUND(Tuning!$B$21*POWER(Tuning!$B$22,D37-1),0) | J37: 0.1 | L37: 2.2 | M37: 0.67 | Q37: 1 | S37: 2 | U37: Yes | V37: Yes
A38: Brush Beater | B38: Slug | C38: reach | D38: 4 | E38: Long Barrel | F38: =ROUND(Tuning!$B$21*POWER(Tuning!$B$22,D38-1),0) | J38: 0.8 | L38: 1.1818182 | M38: 1 | S38: 3 | BB38: A | BC38: Tighter, longer slugs that go through 3 dinos
A39: Brush Beater | B39: Slug | C39: reach | D39: 5 | E39: Railslug | F39: =ROUND(Tuning!$B$21*POWER(Tuning!$B$22,D39-1),0) | J39: 0.625 | L39: 1.1538462 | M39: 1.4925373 | S39: 6 | BB39: A | BC39: Slugs go through 6 dinos
A40: Brush Beater | B40: Buckshot | C40: crowds | D40: 1 | E40: Tight Choke | F40: =ROUND(Tuning!$B$21*POWER(Tuning!$B$22,D40-1),0) | J40: 0.7
A41: Brush Beater | B41: Buckshot | C41: crowds | D41: 2 | E41: Extra Pellets | F41: =ROUND(Tuning!$B$21*POWER(Tuning!$B$22,D41-1),0) | J41: 0.7 | Q41: 9
A42: Brush Beater | B42: Buckshot | C42: crowds | D42: 3 | E42: Dragon's Breath | F42: =ROUND(Tuning!$B$21*POWER(Tuning!$B$22,D42-1),0) | J42: 0.7 | Q42: 9 | W42: 1.5 | X42: 3 | AH42: 1.5 | AI42: 0.35
A43: Brush Beater | B43: Buckshot | C43: crowds | D43: 4 | E43: Auto-Loader | F43: =ROUND(Tuning!$B$21*POWER(Tuning!$B$22,D43-1),0) | G43: 1.6 | I43: 0.8 | J43: 1 | BB43: A | BC43: Fires faster and reloads quicker
A44: Brush Beater | B44: Buckshot | C44: crowds | D44: 5 | E44: Thicket Sweeper | F44: =ROUND(Tuning!$B$21*POWER(Tuning!$B$22,D44-1),0) | G44: 1.375 | H44: 2 | I44: 1 | J44: 1 | N44: auto | BB44: A | BC44: A full-auto drum
A45: Brush Beater | B45: Point Blank | C45: burst | D45: 1 | E45: Speed Shells | F45: =ROUND(Tuning!$B$21*POWER(Tuning!$B$22,D45-1),0) | I45: 0.6
A46: Brush Beater | B46: Point Blank | C46: burst | D46: 2 | E46: Extended Tube | F46: =ROUND(Tuning!$B$21*POWER(Tuning!$B$22,D46-1),0) | H46: 1.5 | I46: 0.6
A47: Brush Beater | B47: Point Blank | C47: burst | D47: 3 | E47: Double Barrel | F47: =ROUND(Tuning!$B$21*POWER(Tuning!$B$22,D47-1),0) | H47: 1.5 | I47: 0.6 | R47: 2
A48: Brush Beater | B48: Point Blank | C48: burst | D48: 4 | E48: Kickback | F48: =ROUND(Tuning!$B$21*POWER(Tuning!$B$22,D48-1),0) | H48: 1 | I48: 1 | Z48: 4 | BB48: A | BC48: Blasts knock dinos back
A49: Brush Beater | B49: Point Blank | C49: burst | D49: 5 | E49: Frag Shells | F49: =ROUND(Tuning!$B$21*POWER(Tuning!$B$22,D49-1),0) | H49: 1 | I49: 1 | Y49: 5 | BB49: A | BC49: Shells explode on impact
A50: Field Medic | B50: Triage | C50: ability | D50: 1 | E50: Clean Bandages | F50: =ROUND(Tuning!$B$21*POWER(Tuning!$B$22,D50-1),0) | AJ50: 1.25
A51: Field Medic | B51: Triage | C51: ability | D51: 2 | E51: Belt Pouch | F51: =ROUND(Tuning!$B$21*POWER(Tuning!$B$22,D51-1),0) | AC51: 0.8 | AJ51: 1.25
A52: Field Medic | B52: Triage | C52: ability | D52: 3 | E52: Patch Up | F52: =ROUND(Tuning!$B$21*POWER(Tuning!$B$22,D52-1),0) | AC52: 0.8 | AJ52: 1.25 | AL52: Yes
A53: Field Medic | B53: Triage | C53: ability | D53: 4 | E53: Triage Tent | F53: =ROUND(Tuning!$B$21*POWER(Tuning!$B$22,D53-1),0) | AC53: 1 | AJ53: 1 | AK53: 1.5 | BB53: A | BC53: Your Triage Kit heals a wider area
A54: Field Medic | B54: Triage | C54: ability | D54: 5 | E54: Second Wind | F54: =ROUND(Tuning!$B$21*POWER(Tuning!$B$22,D54-1),0) | AC54: 1 | AJ54: 1 | AK54: 1 | AM54: 30 | AN54: 8 | BB54: A | BC54: Everyone you heal takes less damage for a while
A55: Field Medic | B55: Lever Action | C55: handling | D55: 1 | E55: Oiled Lever | F55: =ROUND(Tuning!$B$21*POWER(Tuning!$B$22,D55-1),0) | G55: 1.2
A56: Field Medic | B56: Lever Action | C56: handling | D56: 2 | E56: Loading Gate | F56: =ROUND(Tuning!$B$21*POWER(Tuning!$B$22,D56-1),0) | G56: 1.2 | H56: 1.5 | I56: 0.75
A57: Field Medic | B57: Lever Action | C57: handling | D57: 3 | E57: Rapid Cycle | F57: =ROUND(Tuning!$B$21*POWER(Tuning!$B$22,D57-1),0) | G57: 1.2 | H57: 1.5 | I57: 0.75 | N57: burst | O57: 2
A58: Field Medic | B58: Lever Action | C58: handling | D58: 4 | E58: Smooth Action | F58: =ROUND(Tuning!$B$21*POWER(Tuning!$B$22,D58-1),0) | G58: 1 | H58: 1 | I58: 1 | K58: 0.5 | BB58: A | BC58: Half the kick
A59: Field Medic | B59: Lever Action | C59: handling | D59: 5 | E59: Runaway Lever | F59: =ROUND(Tuning!$B$21*POWER(Tuning!$B$22,D59-1),0) | G59: 1.3333333 | H59: 1 | I59: 1 | K59: 1 | N59: auto | O59: 0 | BB59: A | BC59: Goes full auto
A60: Field Medic | B60: Muzzle | C60: protective rounds | D60: 1 | E60: Tranq Tips | F60: =ROUND(Tuning!$B$21*POWER(Tuning!$B$22,D60-1),0) | AO60: 20 | AP60: 1
A61: Field Medic | B61: Muzzle | C61: protective rounds | D61: 2 | E61: Double Dose | F61: =ROUND(Tuning!$B$21*POWER(Tuning!$B$22,D61-1),0) | AO61: 30 | AP61: 1.5
A62: Field Medic | B62: Muzzle | C62: protective rounds | D62: 3 | E62: Jaw Lock | F62: =ROUND(Tuning!$B$21*POWER(Tuning!$B$22,D62-1),0) | AO62: 30 | AP62: 1.5 | AQ62: 2
A63: Field Medic | B63: Muzzle | C63: protective rounds | D63: 4 | E63: Long Dose | F63: =ROUND(Tuning!$B$21*POWER(Tuning!$B$22,D63-1),0) | AQ63: 3 | BB63: A | BC63: Jaw Lock keeps a dino's jaws shut for longer
A64: Field Medic | B64: Muzzle | C64: protective rounds | D64: 5 | E64: Lullaby Rounds | F64: =ROUND(Tuning!$B$21*POWER(Tuning!$B$22,D64-1),0) | AR64: 6 | BB64: A | BC64: Jaw Lock spreads to nearby dinos
A65: Tracker | B65: Gunslinger | C65: handling | D65: 6 | E65: Hot Swap | F65: =ROUND(Tuning!$B$21*POWER(Tuning!$B$22,D65-1),0) | G65: 1 | H65: 1 | I65: 0.8 | AU65: Yes
A66: Tracker | B66: Marksman | C66: accuracy | D66: 6 | E66: Heart Shot | F66: =ROUND(Tuning!$B$21*POWER(Tuning!$B$22,D66-1),0) | J66: 1 | K66: 1 | L66: 1 | AB66: 1 | AS66: 2 | AZ66: 0
A67: Tracker | B67: Trick Shot | C67: utility | D67: 6 | E67: Bounce Back | F67: =ROUND(Tuning!$B$21*POWER(Tuning!$B$22,D67-1),0) | H67: 1 | I67: 1 | AC67: 1 | AV67: 1
A68: Big Game Hunter | B68: Stalker | C68: control | D68: 6 | E68: Big Five | F68: =ROUND(Tuning!$B$21*POWER(Tuning!$B$22,D68-1),0) | G68: 1 | J68: 1 | K68: 1 | L68: 1 | M68: 1 | O68: 5 | AW68: Yes
A69: Big Game Hunter | B69: Heavy | C69: sustain | D69: 6 | E69: Endless Belt | F69: =ROUND(Tuning!$B$21*POWER(Tuning!$B$22,D69-1),0) | H69: 1 | I69: 1 | AE69: 1 | AF69: 1 | AX69: Yes
A70: Big Game Hunter | B70: Special Ammo | C70: rounds | D70: 6 | E70: Dynamite Rounds | F70: =ROUND(Tuning!$B$21*POWER(Tuning!$B$22,D70-1),0) | L70: 1 | M70: 1 | Y70: 6
A71: Brush Beater | B71: Slug | C71: reach | D71: 6 | E71: Thunder Slug | F71: =ROUND(Tuning!$B$21*POWER(Tuning!$B$22,D71-1),0) | J71: 1 | L71: 1 | M71: 1 | AS71: 2 | AY71: 0
A72: Brush Beater | B72: Buckshot | C72: crowds | D72: 6 | E72: Wildfire Drum | F72: =ROUND(Tuning!$B$21*POWER(Tuning!$B$22,D72-1),0) | G72: 1 | H72: 1.5 | I72: 1 | J72: 1 | AT72: 4
A73: Brush Beater | B73: Point Blank | C73: burst | D73: 6 | E73: Quad Barrel | F73: =ROUND(Tuning!$B$21*POWER(Tuning!$B$22,D73-1),0) | H73: 1 | I73: 1.25 | R73: 4
A74: Field Medic | B74: Triage | C74: ability | D74: 6 | E74: Rapid Response | F74: =ROUND(Tuning!$B$21*POWER(Tuning!$B$22,D74-1),0) | AC74: 1 | AJ74: 1 | AK74: 1 | BA74: 2
A75: Field Medic | B75: Lever Action | C75: handling | D75: 6 | E75: Bottomless Tube | F75: =ROUND(Tuning!$B$21*POWER(Tuning!$B$22,D75-1),0) | G75: 1 | H75: 1.5 | I75: 0.5 | K75: 1
A76: Field Medic | B76: Muzzle | C76: protective rounds | D76: 6 | E76: Lights Out | F76: =ROUND(Tuning!$B$21*POWER(Tuning!$B$22,D76-1),0) | AQ76: 4 | AR76: 9
A77: Tracker | B77: Gunslinger | C77: handling | D77: 4 | E77: Deep Cylinders | F77: =F8 | G77: 1.15 | H77: 1.5 | BB77: B | BC77: Both guns hold 50% more and fire 15% faster
A78: Tracker | B78: Gunslinger | C78: handling | D78: 4 | E78: Crossdraw | F78: =F8 | G78: 1.15 | I78: 0.65 | BB78: C | BC78: Reload 35% faster, fire 15% faster
A79: Tracker | B79: Gunslinger | C79: handling | D79: 5 | E79: Twin Burst | F79: =F9 | G79: 1.3 | H79: 1.3 | N79: burst | O79: 3 | BB79: B | BC79: Each click fires a 3-round burst, 30% faster
A80: Tracker | B80: Gunslinger | C80: handling | D80: 5 | E80: Steady Pair | F80: =F9 | G80: 1.1 | J80: 0.8 | K80: 0.5 | BB80: C | BC80: Half the kick, tighter aim, 10% faster
A81: Tracker | B81: Marksman | C81: accuracy | D81: 4 | E81: Quick Cock | F81: =F13 | G81: 1.2 | BB81: B | BC81: Fire 20% faster, scope and all
A82: Tracker | B82: Marksman | C82: accuracy | D82: 4 | E82: Breath Control | F82: =F13 | K82: 0.5 | L82: 1.35 | BB82: C | BC82: Half the kick; the scope reaches 35% further
A83: Tracker | B83: Marksman | C83: accuracy | D83: 5 | E83: Quick Scope | F83: =F14 | G83: 1.7 | K83: 0.7 | BB83: B | BC83: Fire 70% faster with 30% less kick
A84: Tracker | B84: Marksman | C84: accuracy | D84: 5 | E84: Hunter's Mark | F84: =F14 | J84: 0.8 | AA84: 35 | BB84: C | BC84: Hits mark dinos: +35% from everything
A85: Tracker | B85: Trick Shot | C85: utility | D85: 4 | E85: Bank Shot | F85: =F18 | T85: 2 | BB85: B | BC85: Ricochets bounce twice
A86: Tracker | B86: Trick Shot | C86: utility | D86: 4 | E86: Quick Fingers | F86: =F18 | G86: 1.07 | I86: 0.7 | BB86: C | BC86: Reload 30% faster, fire a bit faster
A87: Tracker | B87: Trick Shot | C87: utility | D87: 5 | E87: Pinball | F87: =F19 | G87: 1.17 | H87: 1.5 | T87: 3 | BB87: B | BC87: 3 bounces, a bigger cylinder, faster shots
A88: Tracker | B88: Trick Shot | C88: utility | D88: 5 | E88: Dart Storm | F88: =F19 | G88: 1.15 | T88: 3 | AC88: 0.75 | BB88: C | BC88: 3 bounces, faster shots, Tracking Dart sooner
A89: Big Game Hunter | B89: Stalker | C89: control | D89: 4 | E89: Snap Bursts | F89: =F23 | G89: 1.2 | BB89: B | BC89: Bursts come 20% faster
A90: Big Game Hunter | B90: Stalker | C90: control | D90: 4 | E90: Quick Mag | F90: =F23 | I90: 0.75 | BB90: C | BC90: Reload 25% faster
A91: Big Game Hunter | B91: Stalker | C91: control | D91: 5 | E91: Marking Burst | F91: =F24 | G91: 1.1 | H91: 1.3 | O91: 4 | AA91: 25 | BB91: B | BC91: 4-round bursts that mark: +25% from everything
A92: Big Game Hunter | B92: Stalker | C92: control | D92: 5 | E92: Rapid Volley | F92: =F24 | G92: 1.35 | H92: 1.5 | K92: 0.5 | BB92: C | BC92: Bursts 35% faster, half the kick, bigger mag
A93: Big Game Hunter | B93: Heavy | C93: sustain | D93: 4 | E93: Steady Sling | F93: =F28 | K93: 0.65 | BB93: B | BC93: 35% less kick, moving or not
A94: Big Game Hunter | B94: Heavy | C94: sustain | D94: 4 | E94: Quick Belt | F94: =F28 | I94: 0.7 | K94: 0.8 | BB94: C | BC94: Belt changes 30% faster; 20% less kick
A95: Big Game Hunter | B95: Heavy | C95: sustain | D95: 5 | E95: Hot Barrel | F95: =F29 | G95: 1.5 | H95: 1.3 | AF95: 1.6 | BB95: B | BC95: 50% faster at once, spins up to +60% more
A96: Big Game Hunter | B96: Heavy | C96: sustain | D96: 5 | E96: War Drum | F96: =F29 | AC96: 0.5 | AF96: 2.3 | BB96: C | BC96: Rally Cry twice as often; spins up to +130%
A97: Big Game Hunter | B97: Special Ammo | C97: rounds | D97: 4 | E97: Phosphor Rounds | F97: =F33 | W97: 1.1 | X97: 3 | BB97: B | BC97: Fires burn 10% hotter and 50% longer
A98: Big Game Hunter | B98: Special Ammo | C98: rounds | D98: 4 | E98: Bright Tracers | F98: =F33 | AA98: 30 | BB98: C | BC98: Hits mark dinos: +30% from everything
A99: Big Game Hunter | B99: Special Ammo | C99: rounds | D99: 5 | E99: Fire Tips | F99: =F34 | X99: 2.5 | Y99: 3 | BB99: B | BC99: Small blasts; dinos burn 25% longer
A100: Big Game Hunter | B100: Special Ammo | C100: rounds | D100: 5 | E100: Flat Tips | F100: =F34 | L100: 1.25 | Y100: 3 | BB100: C | BC100: Small blasts; rounds fly 25% further
A101: Brush Beater | B101: Slug | C101: reach | D101: 4 | E101: Quick Pump | F101: =F38 | G101: 1.25 | BB101: B | BC101: Pump 25% faster
...

Sheet Mastery
A1: HERO MASTERY — permanent, per hero
A2: Bought with Amber. Head starts and unlocks only — never gun damage multipliers.
A4: Level | B4: Amber cost | C4: Cumulative amber | D4: Matches to earn | E4: Unlock at this level | F4: Upgrade discount % | G4: Ability cooldown x | H4: Free first upgrade | I4: Crossover cap | J4: Pick-up reach + | K4: Heal per round + | L4: Respawn x | M4: Repair cost x
A5: 1 | B5: {=ROUND('Tuning'!$B$27*POWER('Tuning'!$B$28,A5-1),0)} | C5: {=B5} | D5: =ROUND(C5/Tuning!$B$26,1) | E5: -5% on this hero's upgrade costs | F5: 5 | G5: 1 | H5: No | I5: 2 | L5: 1 | M5: 1
A6: 2 | B6: {=ROUND('Tuning'!$B$27*POWER('Tuning'!$B$28,A6-1),0)} | C6: {=C5+B6} | D6: =ROUND(C6/Tuning!$B$26,1) | E6: -10% cumulative | F6: 10 | G6: 1 | H6: No | I6: 2 | L6: 1 | M6: 1
A7: 3 | B7: {=ROUND('Tuning'!$B$27*POWER('Tuning'!$B$28,A7-1),0)} | C7: {=C6+B7} | D7: =ROUND(C7/Tuning!$B$26,1) | E7: -15% cumulative | F7: 15 | G7: 1 | H7: No | I7: 2 | L7: 1 | M7: 1
A8: 4 | B8: {=ROUND('Tuning'!$B$27*POWER('Tuning'!$B$28,A8-1),0)} | C8: {=C7+B8} | D8: =ROUND(C8/Tuning!$B$26,1) | E8: -20% cumulative (cap on cost reduction) | F8: 20 | G8: 1 | H8: No | I8: 2 | L8: 1 | M8: 1
A9: 5 | B9: {=ROUND('Tuning'!$B$27*POWER('Tuning'!$B$28,A9-1),0)} | C9: {=C8+B9} | D9: =ROUND(C9/Tuning!$B$26,1) | E9: Ability cooldown -15% | F9: 20 | G9: 0.85 | H9: No | I9: 2 | L9: 1 | M9: 1
A10: 6 | B10: {=ROUND('Tuning'!$B$27*POWER('Tuning'!$B$28,A10-1),0)} | C10: {=C9+B10} | D10: =ROUND(C10/Tuning!$B$26,1) | E10: Long Arms I: pick up chests and med kits from 2 studs away | F10: 20 | G10: 0.85 | H10: No | I10: 2 | J10: 2 | L10: 1 | M10: 1
A11: 7 | B11: {=ROUND('Tuning'!$B$27*POWER('Tuning'!$B$28,A11-1),0)} | C11: {=C10+B11} | D11: =ROUND(C11/Tuning!$B$26,1) | E11: First Aid I: heal 5 more HP when a round is cleared | F11: 20 | G11: 0.85 | H11: No | I11: 2 | J11: 2 | K11: 5 | L11: 1 | M11: 1
A12: 8 | B12: {=ROUND('Tuning'!$B$27*POWER('Tuning'!$B$28,A12-1),0)} | C12: {=C11+B12} | D12: =ROUND(C12/Tuning!$B$26,1) | E12: Back in Action I: respawn 10% sooner | F12: 20 | G12: 0.85 | H12: No | I12: 2 | J12: 2 | K12: 5 | L12: 0.9 | M12: 1
A13: 9 | B13: {=ROUND('Tuning'!$B$27*POWER('Tuning'!$B$28,A13-1),0)} | C13: {=C12+B13} | D13: =ROUND(C13/Tuning!$B$26,1) | E13: Handyman I: repairs cost 5% less | F13: 20 | G13: 0.85 | H13: No | I13: 2 | J13: 2 | K13: 5 | L13: 0.9 | M13: 0.95
A14: 10 | B14: {=ROUND('Tuning'!$B$27*POWER('Tuning'!$B$28,A14-1),0)} | C14: {=C13+B14} | D14: =ROUND(C14/Tuning!$B$26,1) | E14: Start every match with your first upgrade free, plus this hero's mastery-10 ability perk | F14: 20 | G14: 0.85 | H14: Yes | I14: 2 | J14: 2 | K14: 5 | L14: 0.9 | M14: 0.95
A15: 11 | B15: {=ROUND('Tuning'!$B$27*POWER('Tuning'!$B$28,A15-1),0)} | C15: {=C14+B15} | D15: =ROUND(C15/Tuning!$B$26,1) | E15: Long Arms II: pick up chests and med kits from 4 studs away | F15: 20 | G15: 0.85 | H15: Yes | I15: 2 | J15: 4 | K15: 5 | L15: 0.9 | M15: 0.95
A16: 12 | B16: {=ROUND('Tuning'!$B$27*POWER('Tuning'!$B$28,A16-1),0)} | C16: {=C15+B16} | D16: =ROUND(C16/Tuning!$B$26,1) | E16: First Aid II: heal 10 more HP when a round is cleared | F16: 20 | G16: 0.85 | H16: Yes | I16: 2 | J16: 4 | K16: 10 | L16: 0.9 | M16: 0.95
A17: 13 | B17: {=ROUND('Tuning'!$B$27*POWER('Tuning'!$B$28,A17-1),0)} | C17: {=C16+B17} | D17: =ROUND(C17/Tuning!$B$26,1) | E17: Back in Action II: respawn 20% sooner | F17: 20 | G17: 0.85 | H17: Yes | I17: 2 | J17: 4 | K17: 10 | L17: 0.8 | M17: 0.95
A18: 14 | B18: {=ROUND('Tuning'!$B$27*POWER('Tuning'!$B$28,A18-1),0)} | C18: {=C17+B18} | D18: =ROUND(C18/Tuning!$B$26,1) | E18: Handyman II: repairs cost 10% less | F18: 20 | G18: 0.85 | H18: Yes | I18: 2 | J18: 4 | K18: 10 | L18: 0.8 | M18: 0.9
A19: 15 | B19: {=ROUND('Tuning'!$B$27*POWER('Tuning'!$B$28,A19-1),0)} | C19: {=C18+B19} | D19: =ROUND(C19/Tuning!$B$26,1) | E19: Ability cooldown -30%, plus this hero's mastery-15 ability perk | F19: 20 | G19: 0.7 | H19: Yes | I19: 2 | J19: 4 | K19: 10 | L19: 0.8 | M19: 0.9
A20: 16 | B20: {=ROUND('Tuning'!$B$27*POWER('Tuning'!$B$28,A20-1),0)} | C20: {=C19+B20} | D20: =ROUND(C20/Tuning!$B$26,1) | E20: Long Arms III: pick up chests and med kits from 6 studs away | F20: 20 | G20: 0.7 | H20: Yes | I20: 2 | J20: 6 | K20: 10 | L20: 0.8 | M20: 0.9
A21: 17 | B21: {=ROUND('Tuning'!$B$27*POWER('Tuning'!$B$28,A21-1),0)} | C21: {=C20+B21} | D21: =ROUND(C21/Tuning!$B$26,1) | E21: First Aid III: heal 15 more HP when a round is cleared | F21: 20 | G21: 0.7 | H21: Yes | I21: 2 | J21: 6 | K21: 15 | L21: 0.8 | M21: 0.9
A22: 18 | B22: {=ROUND('Tuning'!$B$27*POWER('Tuning'!$B$28,A22-1),0)} | C22: {=C21+B22} | D22: =ROUND(C22/Tuning!$B$26,1) | E22: Back in Action III: respawn 30% sooner | F22: 20 | G22: 0.7 | H22: Yes | I22: 2 | J22: 6 | K22: 15 | L22: 0.7 | M22: 0.9
... A24: 20 | B24: {=ROUND('Tuning'!$B$27*POWER('Tuning'!$B$28,A24-1),0)} | C24: {=C23+B24} | D24: =ROUND(C24/Tuning!$B$26,1) | E24: Mastery skin (gold gun), and this hero's second upgrade path can reach tier 3 | F24: 20 | G24: 0.7 | H24: Yes | I24: 3 | J24: 6 | K24: 15 | L24: 0.7 | M24: 0.85
A26: 'Matches to earn' assumes an average run reaching round 25.

Sheet Enemies
A1: DINOSAURS — each tier is its own species
A2: Base HP is the species' total HP across all its sizes. A hit that empties a size shrinks the dino one size (same species, HP split evenly across sizes); the smallest size dies. Keys stay internal.
A4: Key | B4: Enemy | C4: Base HP | D4: Scaled HP | E4: Speed x | F4: Splits into | G4: Split count | H4: Effective HP | I4: Cash value | J4: Flying | K4: Note | L4: Armored | M4: Boss | N4: Sizes | O4: Melee name | P4: Melee damage | Q4: Melee every (s) | R4: Melee reach (studs) | S4: Ranged name | T4: Ranged damage | U4: Ranged every (s) | V4: Ranged reach (studs) | W4: Projectile speed (studs/s) | X4: Impact radius (studs) | Y4: Break resist
A5: HUSK | B5: Compy | C5: 1 | D5: {=ROUND(C5*'Tuning'!$B$16,1)} | E5: 1 | F5: — | G5: 0 | H5: {=D5} | I5: {=ROUND(H5*'Tuning'!$B$8,0)} | J5: No | K5: Tiny pack hunter. The baseline. | L5: No | M5: No | N5: 1 | O5: Nip | P5: 2 | Q5: 1 | R5: 8 | T5: 0 | U5: 0 | V5: 0 | W5: 0 | X5: 0 | Y5: 0
A6: BRUTE | B6: Raptor | C6: 3 | D6: {=ROUND(C6*'Tuning'!$B$16,1)} | E6: 1.2 | F6: — | G6: 0 | H6: {=D6+G6*H5} | I6: {=ROUND(H6*'Tuning'!$B$8,0)} | J6: No | L6: No | M6: No | N6: 2 | O6: Slash | P6: 4 | Q6: 1.2 | R6: 9 | T6: 0 | U6: 0 | V6: 0 | W6: 0 | X6: 0 | Y6: 0
A7: SHIELD | B7: Pachycephalosaurus | C7: 8 | D7: {=ROUND(C7*'Tuning'!$B$16,1)} | E7: 1 | F7: — | G7: 0 | H7: {=D7+G7*H6} | I7: {=ROUND(H7*'Tuning'!$B$8,0)} | J7: No | K7: Head-butter. | L7: No | M7: No | N7: 3 | O7: Head-Butt | P7: 6 | Q7: 1.5 | R7: 9 | S7: Skull Toss | T7: 3 | U7: 8 | V7: 22 | W7: 40 | X7: 3 | Y7: 0
A8: ARMOR | B8: Ankylosaurus | C8: 19 | D8: {=ROUND(C8*'Tuning'!$B$16,1)} | E8: 0.8 | F8: — | G8: 0 | H8: {=D8+G8*H7} | I8: {=ROUND(H8*'Tuning'!$B$8,0)} | J8: No | K8: Armoured: needs armour-piercing (or a stripping Tranq) to hurt. | L8: Yes | M8: No | N8: 3 | O8: Tail Club | P8: 10 | Q8: 2 | R8: 10 | S8: Spike Flick | T8: 4 | U8: 8 | V8: 20 | W8: 50 | X8: 3 | Y8: 1
A9: STORM | B9: Gallimimus | C9: 61 | D9: {=ROUND(C9*'Tuning'!$B$16,1)} | E9: 1.4 | F9: — | G9: 0 | H9: {=D9+G9*H8} | I9: {=ROUND(H9*'Tuning'!$B$8,0)} | J9: No | K9: Fast. Slows matter. | L9: No | M9: No | N9: 3 | O9: Kick | P9: 6 | Q9: 1 | R9: 9 | S9: Gravel Spray | T9: 5 | U9: 6.5 | V9: 25 | W9: 70 | X9: 3 | Y9: 0
A10: LLAMA | B10: Pteranodon | C10: 20 | D10: {=ROUND(C10*'Tuning'!$B$16,1)} | E10: 0.9 | F10: — | G10: 0 | H10: {=D10+G10*H7} | I10: {=ROUND(H10*'Tuning'!$B$8,0)} | J10: Yes | K10: Flying. The Mortar Pit cannot hit it. | L10: No | M10: No | N10: 3 | P10: 0 | Q10: 0 | R10: 0 | S10: Stone Drop | T10: 5 | U10: 6.5 | V10: 18 | W10: 35 | X10: 4 | Y10: 0
A11: ZEP | B11: Triceratops | C11: 280 | D11: {=ROUND(C11*'Tuning'!$B$16,1)} | E11: 0.5 | F11: — | G11: 0 | H11: {=D11+G11*H10} | I11: {=ROUND(H11*'Tuning'!$B$8,0)} | J11: No | K11: Ground boss. | L11: No | M11: Yes | N11: 4 | O11: Gore | P11: 25 | Q11: 2 | R11: 12 | S11: Horn Toss | T11: 20 | U11: 5 | V11: 30 | W11: 45 | X11: 5 | Y11: 1
A12: BARGE | B12: T-Rex | C12: 1820 | D12: {=ROUND(C12*'Tuning'!$B$16,1)} | E12: 0.4 | F12: — | G12: 0 | H12: {=D12+G12*H11} | I12: {=ROUND(H12*'Tuning'!$B$8,0)} | J12: No | K12: Ground boss. Round 40 finale. | L12: No | M12: Yes | N12: 5 | O12: Chomp | P12: 50 | Q12: 2.5 | R12: 14 | S12: Bone Spit | T12: 35 | U12: 6 | V12: 35 | W12: 35 | X12: 8 | Y12: 2
A14: EFFECTIVE HP
A15: Effective HP: total damage to clear one dino, every size included.
A16: Melee: every dino bites the nearest tower or hunter within reach (studs sideways from the track), dealing damage x size/sizes x Difficulty Dino damage x. The Pteranodon only has a ranged attack.
A17: Ranged: mid and high tiers also throw something at the nearest tower or hunter in reach. It flies in a straight line (no homing) to where the target was, and hurts every hunter and standing tower within the impact radius. Values are at the dino's largest size, on Easy.

Sheet Rounds
A1: ROUND TABLE — 40 rounds
A2: Blue counts are the designer's call, not a formula. Everything to the right of them is derived.
A4: Round | B4: Compy | C4: Raptor | D4: Pachy | E4: Ankylosaurus | F4: Gallimimus | G4: Pteranodon | H4: Triceratops | I4: T-Rex | J4: Enemies | K4: HP multiplier | L4: Spawn gap (s) | M4: Total EHP | N4: Round length (s) | O4: Required DPS | P4: Kill income | Q4: Round bonus | R4: Round income | S4: Cumulative cash
A5: 1 | B5: 17 | C5: 7 | D5: 0 | E5: 0 | F5: 0 | G5: 0 | H5: 0 | I5: 0 | J5: {=SUM(B5:I5)} | K5: {=ROUND(POWER('Tuning'!$B$17,A5-1),3)} | L5: 1.19 | M5: {=ROUND((B5*'Enemies'!$H$5+C5*'Enemies'!$H$6+D5*'Enemies'!$H$7+E5*'Enemies'!$H$8+F5*'Enemies'!$H$9+G5*'Enemies'!$H$10+H5*'Enemies'!$H$11+I5*'Enemies'!$H$12)*K5,0)} | N5: {=ROUND(J5*L5+14,0)} | O5: {=IF(N5=0,0,ROUND(M5/N5,1))} | P5: {=ROUND(M5*'Tuning'!$B$8,0)} | Q5: {=ROUND('Tuning'!$B$9+'Tuning'!$B$10*A5,0)} | R5: {=P5+Q5} | S5: {='Tuning'!$B$6+R5}
A6: 2 | B6: 20 | C6: 8 | D6: 0 | E6: 0 | F6: 0 | G6: 0 | H6: 0 | I6: 0 | J6: {=SUM(B6:I6)} | K6: {=ROUND(POWER('Tuning'!$B$17,A6-1),3)} | L6: 1.17 | M6: {=ROUND((B6*'Enemies'!$H$5+C6*'Enemies'!$H$6+D6*'Enemies'!$H$7+E6*'Enemies'!$H$8+F6*'Enemies'!$H$9+G6*'Enemies'!$H$10+H6*'Enemies'!$H$11+I6*'Enemies'!$H$12)*K6,0)} | N6: {=ROUND(J6*L6+14,0)} | O6: {=IF(N6=0,0,ROUND(M6/N6,1))} | P6: {=ROUND(M6*'Tuning'!$B$8,0)} | Q6: {=ROUND('Tuning'!$B$9+'Tuning'!$B$10*A6,0)} | R6: {=P6+Q6} | S6: {=S5+R6}
A7: 3 | B7: 23 | C7: 9 | D7: 0 | E7: 0 | F7: 0 | G7: 0 | H7: 0 | I7: 0 | J7: {=SUM(B7:I7)} | K7: {=ROUND(POWER('Tuning'!$B$17,A7-1),3)} | L7: 1.16 | M7: {=ROUND((B7*'Enemies'!$H$5+C7*'Enemies'!$H$6+D7*'Enemies'!$H$7+E7*'Enemies'!$H$8+F7*'Enemies'!$H$9+G7*'Enemies'!$H$10+H7*'Enemies'!$H$11+I7*'Enemies'!$H$12)*K7,0)} | N7: {=ROUND(J7*L7+14,0)} | O7: {=IF(N7=0,0,ROUND(M7/N7,1))} | P7: {=ROUND(M7*'Tuning'!$B$8,0)} | Q7: {=ROUND('Tuning'!$B$9+'Tuning'!$B$10*A7,0)} | R7: {=P7+Q7} | S7: {=S6+R7}
A8: 4 | B8: 26 | C8: 10 | D8: 0 | E8: 0 | F8: 0 | G8: 0 | H8: 0 | I8: 0 | J8: {=SUM(B8:I8)} | K8: {=ROUND(POWER('Tuning'!$B$17,A8-1),3)} | L8: 1.14 | M8: {=ROUND((B8*'Enemies'!$H$5+C8*'Enemies'!$H$6+D8*'Enemies'!$H$7+E8*'Enemies'!$H$8+F8*'Enemies'!$H$9+G8*'Enemies'!$H$10+H8*'Enemies'!$H$11+I8*'Enemies'!$H$12)*K8,0)} | N8: {=ROUND(J8*L8+14,0)} | O8: {=IF(N8=0,0,ROUND(M8/N8,1))} | P8: {=ROUND(M8*'Tuning'!$B$8,0)} | Q8: {=ROUND('Tuning'!$B$9+'Tuning'!$B$10*A8,0)} | R8: {=P8+Q8} | S8: {=S7+R8}
A9: 5 | B9: 29 | C9: 11 | D9: 0 | E9: 0 | F9: 0 | G9: 0 | H9: 0 | I9: 0 | J9: {=SUM(B9:I9)} | K9: {=ROUND(POWER('Tuning'!$B$17,A9-1),3)} | L9: 1.13 | M9: {=ROUND((B9*'Enemies'!$H$5+C9*'Enemies'!$H$6+D9*'Enemies'!$H$7+E9*'Enemies'!$H$8+F9*'Enemies'!$H$9+G9*'Enemies'!$H$10+H9*'Enemies'!$H$11+I9*'Enemies'!$H$12)*K9,0)} | N9: {=ROUND(J9*L9+14,0)} | O9: {=IF(N9=0,0,ROUND(M9/N9,1))} | P9: {=ROUND(M9*'Tuning'!$B$8,0)} | Q9: {=ROUND('Tuning'!$B$9+'Tuning'!$B$10*A9,0)} | R9: {=P9+Q9} | S9: {=S8+R9}
A10: 6 | B10: 32 | C10: 12 | D10: 0 | E10: 0 | F10: 0 | G10: 0 | H10: 0 | I10: 0 | J10: {=SUM(B10:I10)} | K10: {=ROUND(POWER('Tuning'!$B$17,A10-1),3)} | L10: 1.12 | M10: {=ROUND((B10*'Enemies'!$H$5+C10*'Enemies'!$H$6+D10*'Enemies'!$H$7+E10*'Enemies'!$H$8+F10*'Enemies'!$H$9+G10*'Enemies'!$H$10+H10*'Enemies'!$H$11+I10*'Enemies'!$H$12)*K10,0)} | N10: {=ROUND(J10*L10+14,0)} | O10: {=IF(N10=0,0,ROUND(M10/N10,1))} | P10: {=ROUND(M10*'Tuning'!$B$8,0)} | Q10: {=ROUND('Tuning'!$B$9+'Tuning'!$B$10*A10,0)} | R10: {=P10+Q10} | S10: {=S9+R10}
A11: 7 | B11: 35 | C11: 13 | D11: 2 | E11: 0 | F11: 0 | G11: 0 | H11: 0 | I11: 0 | J11: {=SUM(B11:I11)} | K11: {=ROUND(POWER('Tuning'!$B$17,A11-1),3)} | L11: 1.1 | M11: {=ROUND((B11*'Enemies'!$H$5+C11*'Enemies'!$H$6+D11*'Enemies'!$H$7+E11*'Enemies'!$H$8+F11*'Enemies'!$H$9+G11*'Enemies'!$H$10+H11*'Enemies'!$H$11+I11*'Enemies'!$H$12)*K11,0)} | N11: {=ROUND(J11*L11+14,0)} | O11: {=IF(N11=0,0,ROUND(M11/N11,1))} | P11: {=ROUND(M11*'Tuning'!$B$8,0)} | Q11: {=ROUND('Tuning'!$B$9+'Tuning'!$B$10*A11,0)} | R11: {=P11+Q11} | S11: {=S10+R11}
A12: 8 | B12: 37 | C12: 15 | D12: 4 | E12: 0 | F12: 0 | G12: 0 | H12: 0 | I12: 0 | J12: {=SUM(B12:I12)} | K12: {=ROUND(POWER('Tuning'!$B$17,A12-1),3)} | L12: 1.09 | M12: {=ROUND((B12*'Enemies'!$H$5+C12*'Enemies'!$H$6+D12*'Enemies'!$H$7+E12*'Enemies'!$H$8+F12*'Enemies'!$H$9+G12*'Enemies'!$H$10+H12*'Enemies'!$H$11+I12*'Enemies'!$H$12)*K12,0)} | N12: {=ROUND(J12*L12+14,0)} | O12: {=IF(N12=0,0,ROUND(M12/N12,1))} | P12: {=ROUND(M12*'Tuning'!$B$8,0)} | Q12: {=ROUND('Tuning'!$B$9+'Tuning'!$B$10*A12,0)} | R12: {=P12+Q12} | S12: {=S11+R12}
A13: 9 | B13: 40 | C13: 16 | D13: 6 | E13: 0 | F13: 0 | G13: 1 | H13: 0 | I13: 0 | J13: {=SUM(B13:I13)} | K13: {=ROUND(POWER('Tuning'!$B$17,A13-1),3)} | L13: 1.07 | M13: {=ROUND((B13*'Enemies'!$H$5+C13*'Enemies'!$H$6+D13*'Enemies'!$H$7+E13*'Enemies'!$H$8+F13*'Enemies'!$H$9+G13*'Enemies'!$H$10+H13*'Enemies'!$H$11+I13*'Enemies'!$H$12)*K13,0)} | N13: {=ROUND(J13*L13+14,0)} | O13: {=IF(N13=0,0,ROUND(M13/N13,1))} | P13: {=ROUND(M13*'Tuning'!$B$8,0)} | Q13: {=ROUND('Tuning'!$B$9+'Tuning'!$B$10*A13,0)} | R13: {=P13+Q13} | S13: {=S12+R13}
A14: 10 | B14: 43 | C14: 17 | D14: 9 | E14: 2 | F14: 0 | G14: 2 | H14: 0 | I14: 0 | J14: {=SUM(B14:I14)} | K14: {=ROUND(POWER('Tuning'!$B$17,A14-1),3)} | L14: 1.06 | M14: {=ROUND((B14*'Enemies'!$H$5+C14*'Enemies'!$H$6+D14*'Enemies'!$H$7+E14*'Enemies'!$H$8+F14*'Enemies'!$H$9+G14*'Enemies'!$H$10+H14*'Enemies'!$H$11+I14*'Enemies'!$H$12)*K14,0)} | N14: {=ROUND(J14*L14+14,0)} | O14: {=IF(N14=0,0,ROUND(M14/N14,1))} | P14: {=ROUND(M14*'Tuning'!$B$8,0)} | Q14: {=ROUND('Tuning'!$B$9+'Tuning'!$B$10*A14,0)} | R14: {=P14+Q14} | S14: {=S13+R14}
A15: 11 | B15: 19 | C15: 16 | D15: 14 | E15: 6 | F15: 0 | G15: 5 | H15: 0 | I15: 0 | J15: {=SUM(B15:I15)} | K15: {=ROUND(POWER('Tuning'!$B$17,A15-1),3)} | L15: 1.05 | M15: {=ROUND((B15*'Enemies'!$H$5+C15*'Enemies'!$H$6+D15*'Enemies'!$H$7+E15*'Enemies'!$H$8+F15*'Enemies'!$H$9+G15*'Enemies'!$H$10+H15*'Enemies'!$H$11+I15*'Enemies'!$H$12)*K15,0)} | N15: {=ROUND(J15*L15+14,0)} | O15: {=IF(N15=0,0,ROUND(M15/N15,1))} | P15: {=ROUND(M15*'Tuning'!$B$8,0)} | Q15: {=ROUND('Tuning'!$B$9+'Tuning'!$B$10*A15,0)} | R15: {=P15+Q15} | S15: {=S14+R15}
A16: 12 | B16: 20 | C16: 17 | D16: 16 | E16: 7 | F16: 0 | G16: 5 | H16: 0 | I16: 0 | J16: {=SUM(B16:I16)} | K16: {=ROUND(POWER('Tuning'!$B$17,A16-1),3)} | L16: 1.03 | M16: {=ROUND((B16*'Enemies'!$H$5+C16*'Enemies'!$H$6+D16*'Enemies'!$H$7+E16*'Enemies'!$H$8+F16*'Enemies'!$H$9+G16*'Enemies'!$H$10+H16*'Enemies'!$H$11+I16*'Enemies'!$H$12)*K16,0)} | N16: {=ROUND(J16*L16+14,0)} | O16: {=IF(N16=0,0,ROUND(M16/N16,1))} | P16: {=ROUND(M16*'Tuning'!$B$8,0)} | Q16: {=ROUND('Tuning'!$B$9+'Tuning'!$B$10*A16,0)} | R16: {=P16+Q16} | S16: {=S15+R16}
A17: 13 | B17: 22 | C17: 18 | D17: 18 | E17: 9 | F17: 0 | G17: 6 | H17: 0 | I17: 0 | J17: {=SUM(B17:I17)} | K17: {=ROUND(POWER('Tuning'!$B$17,A17-1),3)} | L17: 1.02 | M17: {=ROUND((B17*'Enemies'!$H$5+C17*'Enemies'!$H$6+D17*'Enemies'!$H$7+E17*'Enemies'!$H$8+F17*'Enemies'!$H$9+G17*'Enemies'!$H$10+H17*'Enemies'!$H$11+I17*'Enemies'!$H$12)*K17,0)} | N17: {=ROUND(J17*L17+14,0)} | O17: {=IF(N17=0,0,ROUND(M17/N17,1))} | P17: {=ROUND(M17*'Tuning'!$B$8,0)} | Q17: {=ROUND('Tuning'!$B$9+'Tuning'!$B$10*A17,0)} | R17: {=P17+Q17} | S17: {=S16+R17}
... A44: 40 | B44: 0 | C44: 16 | D44: 26 | E44: 31 | F44: 31 | G44: 18 | H44: 8 | I44: 1 | J44: {=SUM(B44:I44)} | K44: {=ROUND(POWER('Tuning'!$B$17,A44-1),3)} | L44: 0.64 | M44: {=ROUND((B44*'Enemies'!$H$5+C44*'Enemies'!$H$6+D44*'Enemies'!$H$7+E44*'Enemies'!$H$8+F44*'Enemies'!$H$9+G44*'Enemies'!$H$10+H44*'Enemies'!$H$11+I44*'Enemies'!$H$12)*K44,0)} | N44: {=ROUND(J44*L44+14,0)} | O44: {=IF(N44=0,0,ROUND(M44/N44,1))} | P44: {=ROUND(M44*'Tuning'!$B$8,0)} | Q44: {=ROUND('Tuning'!$B$9+'Tuning'!$B$10*A44,0)} | R44: {=P44+Q44} | S44: {=S43+R44}
A46: Shaded rows are band transitions, where a new enemy type enters and difficulty spikes. That sawtooth is intentional.
A47: Enemy counts plateau at 130 because UEFN, not design, sets the ceiling. Late difficulty comes from the HP multiplier instead — the same reason BTD6 late rounds are a few BADs and not two thousand bloons.
A48: Round length assumes spawn gap x enemy count plus 14s of clear time: measured 2026-09-28, a round ends ~14s after its last spawn when nothing leaks. A dino that leaks walks the whole track (~44s), which only matters for leaks. Rough, but consistent across rounds, which is what matters for comparison.

Sheet Difficulty
A1: DIFFICULTY — Easy is the baseline; every other level scales from it
A2: Chosen before round 1. Player-count scaling (Tuning, CO-OP) applies on top.
A4: Difficulty | B4: Enemy HP x | C4: Enemy count x | D4: Enemy speed x | E4: Promote chance | F4: Cash x | G4: Starting lives | H4: Note | I4: Clear reward (amber) | J4: Dino damage x | K4: Starting cash | L4: Tower damage x | M4: Hero damage x | N4: Clear XP
A5: Easy | B5: 1 | C5: 1 | D5: 1 | E5: 0 | F5: 1 | G5: 40 | H5: The baseline. Current balance. | I5: 50 | J5: 1 | K5: 450 | L5: 1 | M5: 1 | N5: 500
A6: Normal | B6: 1.25 | C6: 1.3 | D6: 1.05 | E6: 0.1 | F6: 0.9 | G6: 30 | H6: 10% of enemies spawn one tier tougher. | I6: 100 | J6: 1.25 | K6: 450 | L6: 1 | M6: 1 | N6: 1000
A7: Hard | B7: 1.6 | C7: 1.7 | D7: 1.1 | E7: 0.2 | F7: 0.8 | G7: 20 | I7: 150 | J7: 1.6 | K7: 850 | L7: 1 | M7: 1 | N7: 1500
A8: Chaos | B8: 2.2 | C8: 2.5 | D8: 1.2 | E8: 0.35 | F8: 0.75 | G8: 10 | H8: Meant for big lobbies. | I8: 200 | J8: 2.2 | K8: 450 | L8: 0.6 | M8: 1.5 | N8: 2000
A11: Enemy count x raises density: the round's spawn gap shrinks by the same factor, so rounds get busier, not longer.
A12: Promote chance: each spawn has this chance to become the next ground species up (Compy > Raptor > Pachy > Ankylosaurus > Gallimimus). Flyers and bosses are never promoted.
A13: Cash x scales kill income and the round bonus.

Sheet Balance Check
A1: BALANCE CHECK — is each round actually winnable?
A2: An economy smoke test, not a difficulty simulator. Open it after every change to Tuning.
A4: Round | B4: Required DPS | C4: Ref tier | D4: Cost per DPS | E4: Cash needed | F4: Cumulative cash | G4: Cash in towers | H4: Affordability | I4: Status
A5: 1 | B5: {='Rounds'!O5} | C5: {=MIN(5,A5/'Tuning'!$B$32)} | D5: =ROUND('Towers'!$C$13*POWER('Tuning'!$B$12/'Tuning'!$B$13,C5),1) | E5: {=ROUND(B5*D5/'Tuning'!$B$31,0)} | F5: {='Rounds'!S5} | G5: {=ROUND(F5*'Tuning'!$B$30,0)} | H5: {=IF(E5=0,0,G5/E5)} | I5: {=IF(H5<1,"TIGHT",IF(H5<2,"OK","EASY"))}
A6: 2 | B6: {='Rounds'!O6} | C6: {=MIN(5,A6/'Tuning'!$B$32)} | D6: =ROUND('Towers'!$C$13*POWER('Tuning'!$B$12/'Tuning'!$B$13,C6),1) | E6: {=ROUND(B6*D6/'Tuning'!$B$31,0)} | F6: {='Rounds'!S6} | G6: {=ROUND(F6*'Tuning'!$B$30,0)} | H6: {=IF(E6=0,0,G6/E6)} | I6: {=IF(H6<1,"TIGHT",IF(H6<2,"OK","EASY"))}
A7: 3 | B7: {='Rounds'!O7} | C7: {=MIN(5,A7/'Tuning'!$B$32)} | D7: =ROUND('Towers'!$C$13*POWER('Tuning'!$B$12/'Tuning'!$B$13,C7),1) | E7: {=ROUND(B7*D7/'Tuning'!$B$31,0)} | F7: {='Rounds'!S7} | G7: {=ROUND(F7*'Tuning'!$B$30,0)} | H7: {=IF(E7=0,0,G7/E7)} | I7: {=IF(H7<1,"TIGHT",IF(H7<2,"OK","EASY"))}
A8: 4 | B8: {='Rounds'!O8} | C8: {=MIN(5,A8/'Tuning'!$B$32)} | D8: =ROUND('Towers'!$C$13*POWER('Tuning'!$B$12/'Tuning'!$B$13,C8),1) | E8: {=ROUND(B8*D8/'Tuning'!$B$31,0)} | F8: {='Rounds'!S8} | G8: {=ROUND(F8*'Tuning'!$B$30,0)} | H8: {=IF(E8=0,0,G8/E8)} | I8: {=IF(H8<1,"TIGHT",IF(H8<2,"OK","EASY"))}
A9: 5 | B9: {='Rounds'!O9} | C9: {=MIN(5,A9/'Tuning'!$B$32)} | D9: =ROUND('Towers'!$C$13*POWER('Tuning'!$B$12/'Tuning'!$B$13,C9),1) | E9: {=ROUND(B9*D9/'Tuning'!$B$31,0)} | F9: {='Rounds'!S9} | G9: {=ROUND(F9*'Tuning'!$B$30,0)} | H9: {=IF(E9=0,0,G9/E9)} | I9: {=IF(H9<1,"TIGHT",IF(H9<2,"OK","EASY"))}
A10: 6 | B10: {='Rounds'!O10} | C10: {=MIN(5,A10/'Tuning'!$B$32)} | D10: =ROUND('Towers'!$C$13*POWER('Tuning'!$B$12/'Tuning'!$B$13,C10),1) | E10: {=ROUND(B10*D10/'Tuning'!$B$31,0)} | F10: {='Rounds'!S10} | G10: {=ROUND(F10*'Tuning'!$B$30,0)} | H10: {=IF(E10=0,0,G10/E10)} | I10: {=IF(H10<1,"TIGHT",IF(H10<2,"OK","EASY"))}
A11: 7 | B11: {='Rounds'!O11} | C11: {=MIN(5,A11/'Tuning'!$B$32)} | D11: =ROUND('Towers'!$C$13*POWER('Tuning'!$B$12/'Tuning'!$B$13,C11),1) | E11: {=ROUND(B11*D11/'Tuning'!$B$31,0)} | F11: {='Rounds'!S11} | G11: {=ROUND(F11*'Tuning'!$B$30,0)} | H11: {=IF(E11=0,0,G11/E11)} | I11: {=IF(H11<1,"TIGHT",IF(H11<2,"OK","EASY"))}
A12: 8 | B12: {='Rounds'!O12} | C12: {=MIN(5,A12/'Tuning'!$B$32)} | D12: =ROUND('Towers'!$C$13*POWER('Tuning'!$B$12/'Tuning'!$B$13,C12),1) | E12: {=ROUND(B12*D12/'Tuning'!$B$31,0)} | F12: {='Rounds'!S12} | G12: {=ROUND(F12*'Tuning'!$B$30,0)} | H12: {=IF(E12=0,0,G12/E12)} | I12: {=IF(H12<1,"TIGHT",IF(H12<2,"OK","EASY"))}
A13: 9 | B13: {='Rounds'!O13} | C13: {=MIN(5,A13/'Tuning'!$B$32)} | D13: =ROUND('Towers'!$C$13*POWER('Tuning'!$B$12/'Tuning'!$B$13,C13),1) | E13: {=ROUND(B13*D13/'Tuning'!$B$31,0)} | F13: {='Rounds'!S13} | G13: {=ROUND(F13*'Tuning'!$B$30,0)} | H13: {=IF(E13=0,0,G13/E13)} | I13: {=IF(H13<1,"TIGHT",IF(H13<2,"OK","EASY"))}
A14: 10 | B14: {='Rounds'!O14} | C14: {=MIN(5,A14/'Tuning'!$B$32)} | D14: =ROUND('Towers'!$C$13*POWER('Tuning'!$B$12/'Tuning'!$B$13,C14),1) | E14: {=ROUND(B14*D14/'Tuning'!$B$31,0)} | F14: {='Rounds'!S14} | G14: {=ROUND(F14*'Tuning'!$B$30,0)} | H14: {=IF(E14=0,0,G14/E14)} | I14: {=IF(H14<1,"TIGHT",IF(H14<2,"OK","EASY"))}
A15: 11 | B15: {='Rounds'!O15} | C15: {=MIN(5,A15/'Tuning'!$B$32)} | D15: =ROUND('Towers'!$C$13*POWER('Tuning'!$B$12/'Tuning'!$B$13,C15),1) | E15: {=ROUND(B15*D15/'Tuning'!$B$31,0)} | F15: {='Rounds'!S15} | G15: {=ROUND(F15*'Tuning'!$B$30,0)} | H15: {=IF(E15=0,0,G15/E15)} | I15: {=IF(H15<1,"TIGHT",IF(H15<2,"OK","EASY"))}
A16: 12 | B16: {='Rounds'!O16} | C16: {=MIN(5,A16/'Tuning'!$B$32)} | D16: =ROUND('Towers'!$C$13*POWER('Tuning'!$B$12/'Tuning'!$B$13,C16),1) | E16: {=ROUND(B16*D16/'Tuning'!$B$31,0)} | F16: {='Rounds'!S16} | G16: {=ROUND(F16*'Tuning'!$B$30,0)} | H16: {=IF(E16=0,0,G16/E16)} | I16: {=IF(H16<1,"TIGHT",IF(H16<2,"OK","EASY"))}
... A44: 40 | B44: {='Rounds'!O44} | C44: {=MIN(5,A44/'Tuning'!$B$32)} | D44: =ROUND('Towers'!$C$13*POWER('Tuning'!$B$12/'Tuning'!$B$13,C44),1) | E44: {=ROUND(B44*D44/'Tuning'!$B$31,0)} | F44: {='Rounds'!S44} | G44: {=ROUND(F44*'Tuning'!$B$30,0)} | H44: {=IF(E44=0,0,G44/E44)} | I44: {=IF(H44<1,"TIGHT",IF(H44<2,"OK","EASY"))}
A46: WHAT THIS MEASURES
A47: Whether cash income keeps pace with the rising cost of the DPS each round demands. Cost per DPS climbs because tier cost growth (2.30x) outruns tier damage growth (1.90x) — that gap is the real difficulty engine, not enemy count.
A49: TIGHT — under 1.0. The player cannot comfortably afford the DPS this round needs. Correct for the last stretch; a run of these in the midgame means the curve is broken.
A50: OK — between 1.0 and 2.0. Where most rounds should sit.
A51: EASY — over 2.0. Fine for the first ten rounds while players are learning. A block of these at rounds 12-20 is why people quit.
A53: WHAT THIS CANNOT SEE
A54: Tower placement, range coverage, targeting priority, path synergy, or the Chiller's slow multiplying everything near it. It also assumes one competent player buying efficiently.
A55: It catches broken economies. It does not tell you whether the game is fun. Only playtesting does that.

Sheet Daily Haul
A1: DAILY HAUL — the log-in calendar
A2: One claim per UTC day, by hand on the Hunt Board; after the last day it loops. The exporter fails unless every day is below the Easy clear reward and the week is at most two Easy clears (DECISIONS #64, #71).
A4: Day | B4: Amber | C4: Note
A5: 1 | B5: 5
A6: 2 | B6: 5
A7: 3 | B7: 10
A8: 4 | B8: 10
A9: 5 | B9: 15
A10: 6 | B10: 15
A11: 7 | B11: 40 | C11: Big Haul

Sheet Bounties
A1: BOUNTIES — the daily and weekly pools
A2: Each day and week the Hunt Board shows one bounty per slot (Tuning, REWARDS). Slot is never shown. Target: a dino key (pop), a difficulty key = that one or harder (clear), or a round (reachRound: reach that round Count times; blank = reach round Count). {n} in Text is Count. Ids are saved in profiles: never rename one. Counts and Amber: DECISIONS #65, #71, #75.
A4: Id | B4: Pool | C4: Slot | D4: Event | E4: Target | F4: Count | G4: Amber | H4: Title | I4: Text
A5: D_COMPY_SWEEP | B5: daily | C5: easy | D5: pop | E5: HUSK | F5: 150 | G5: 10 | H5: Compy Sweep | I5: Take down {n} Compies
A6: D_RAPTOR_CULL | B6: daily | C6: easy | D6: pop | E6: BRUTE | F6: 100 | G6: 10 | H6: Raptor Cull | I6: Take down {n} Raptors
A7: D_BUSY_DAY | B7: daily | C7: easy | D7: popTotal | F7: 300 | G7: 10 | H7: Busy Day | I7: Take down {n} dinos of any kind
A8: D_GEAR_CHECK | B8: daily | C8: easy | D8: ability | F8: 5 | G8: 10 | H8: Gear Check | I8: Use your ability {n} times
A9: D_PITCH_CAMP | B9: daily | C9: easy | D9: build | F9: 6 | G9: 10 | H9: Pitch Camp | I9: Build {n} towers
A10: D_HEADBUTT_HUNT | B10: daily | C10: medium | D10: pop | E10: SHIELD | F10: 60 | G10: 15 | H10: Headbutt Hunt | I10: Take down {n} Pachycephalosaurs
A11: D_SHELL_CRACKER | B11: daily | C11: medium | D11: pop | E11: ARMOR | F11: 40 | G11: 15 | H11: Shell Cracker | I11: Take down {n} Ankylosaurs
A12: D_CLEAR_SKIES | B12: daily | C12: medium | D12: pop | E12: LLAMA | F12: 30 | G12: 15 | H12: Clear Skies | I12: Take down {n} Pteranodons
A13: D_DEEP_TRAIL_15 | B13: daily | C13: medium | D13: reachRound | F13: 15 | G13: 15 | H13: Deep Trail | I13: Reach round {n}
A14: D_SHARPEN_UP | B14: daily | C14: medium | D14: upgrade | F14: 10 | G14: 15 | H14: Sharpen Up | I14: Upgrade towers {n} times
A15: D_RUN_THEM_DOWN | B15: daily | C15: hard | D15: pop | E15: STORM | F15: 25 | G15: 20 | H15: Run Them Down | I15: Take down {n} Gallimimus
A16: D_DEEP_TRAIL_25 | B16: daily | C16: hard | D16: reachRound | F16: 25 | G16: 20 | H16: Deeper Trail | I16: Reach round {n}
A17: D_PATCH_JOB | B17: daily | C17: hard | D17: repair | F17: 2 | G17: 20 | H17: Patch Job | I17: Repair {n} trampled towers
A18: D_CLEAN_SWEEP | B18: daily | C18: hard | D18: clear | F18: 1 | G18: 20 | H18: Clean Sweep | I18: Clear any track
A19: W_STAMPEDE | B19: weekly | C19: easy | D19: popTotal | F19: 1500 | G19: 40 | H19: Stampede | I19: Take down {n} dinos of any kind
A20: W_GEAR_CHECK | B20: weekly | C20: easy | D20: ability | F20: 30 | G20: 40 | H20: Gear Check | I20: Use your ability {n} times
A21: W_DEEP_TRAIL_2 | B21: weekly | C21: easy | D21: reachRound | E21: 31 | F21: 2 | G21: 40 | H21: Long Trail | I21: Reach round 31 {n} times
A22: W_CLEAN_SWEEP | B22: weekly | C22: medium | D22: clear | F22: 3 | G22: 60 | H22: Clean Sweep | I22: Clear any track {n} times
A23: W_ROUGH_COUNTRY | B23: weekly | C23: medium | D23: clear | E23: NORMAL | F23: 1 | G23: 60 | H23: Rough Country | I23: Clear a track on Normal or harder
A24: W_HORN_BREAKER | B24: weekly | C24: medium | D24: pop | E24: ZEP | F24: 10 | G24: 60 | H24: Horn Breaker | I24: Take down {n} Triceratops (team take-downs count)
A25: W_PATCH_JOB | B25: weekly | C25: medium | D25: repair | F25: 10 | G25: 60 | H25: Patch Job | I25: Repair {n} trampled towers
A26: W_BADLANDS | B26: weekly | C26: hard | D26: clear | E26: HARD | F26: 1 | G26: 80 | H26: Badlands | I26: Clear a track on Hard or harder
A27: W_TYRANTS_END | B27: weekly | C27: hard | D27: pop | E27: BARGE | F27: 1 | G27: 80 | H27: Tyrant's End | I27: Take down a T-Rex (team take-downs count)
A28: W_DEEP_TRAIL_4 | B28: weekly | C28: hard | D28: reachRound | E28: 31 | F28: 4 | G28: 80 | H28: Longest Trail | I28: Reach round 31 {n} times

Sheet Mastery Perks
A1: MASTERY PERKS — a level-10 and a level-15 ability perk per hunter
A2: A hunter with mastery at or above the level has the perk (15 has both). Values are added to the hero's base ability value (Heroes sheet) before path multipliers. Blank = 0. Worth % = 100 x (seconds / base + radius / base + power / base + extra marks x extra mark power) + burn % per s x burn seconds: level 15 must be worth more than level 10, both at most Tuning 'Mastery perk worth cap'. Abilities only: no stun time, no gun damage (DECISIONS #97-#99).
A4: Hero key | B4: Mastery level | C4: Name | D4: Text | E4: Ability seconds + | F4: Ability radius + | G4: Ability power + | H4: Extra marks | I4: Extra mark power x | J4: Extra mark reach | K4: Strike burn % per s | L4: Strike burn (s)
A5: PISTOL | B5: 10 | C5: Sticky Dart | D5: Tracking Dart lasts 2s longer | E5: 2
A6: PISTOL | B6: 15 | C6: Spare Dart | D6: Tracking Dart also marks the nearest dino within 10 studs at 40% strength | H6: 1 | I6: 0.4 | J6: 10
A7: RIFLE | B7: 10 | C7: Hunting Horn | D7: Rally Cry reaches 6 studs further | F7: 6
A8: RIFLE | B8: 15 | C8: Long Rally | D8: Rally Cry lasts 3.5s longer | E8: 3.5
A9: SHOTGUN | B9: 10 | C9: Wide Flare | D9: Flare Strike reaches 2.5 studs further | F9: 2.5
A10: SHOTGUN | B10: 15 | C10: Smoulder | D10: Flare Strike leaves burning ground for 3s (12% of the strike's damage each second) | K10: 12 | L10: 3
A11: MEDIC | B11: 10 | C11: Far Reach | D11: Triage Kit reaches 5 studs further | F11: 5
A12: MEDIC | B12: 15 | C12: Stocked Kit | D12: Triage Kit heals 14 more HP | G12: 14

Sheet Cosmetics
A1: COSMETICS — player level rewards (names are working names, Dino review T59)
A2: One row per reward. Levels 2-99 except multiples of 10: one common each (name colour, gun tint, tracer colour, crosshair colour, tower flag, leaderboard banner). Every 10 to 100: a rare (hunting hat, gun pattern, hit-marker, sprint trail) + a title. 150 and 200: an animated set (legendary) + a title. Nothing else up to 200. Past 200: the row with 'Repeat every' gives a title every N levels, forever ({n} in its name = the level). Cosmetic only: no gameplay effect. No gold: gold is mastery 20's alone (DECISIONS #121). Colour = #RRGGBB; Material = a Roblox material; Pattern: hat Brim/Cap/Crest, hit-marker Cross/Plus/Diamond/Star, set Pulse/Cycle.
A4: Id | B4: Level | C4: Kind | D4: Name | E4: Rarity | F4: Colour | G4: Material | H4: Pattern | I4: Repeat every
A5: NAME_FERN | B5: 2 | C5: Name colour | D5: Fern Name | E5: common | F5: #4F7942
A6: TINT_OCHRE | B6: 3 | C6: Gun tint | D6: Ochre Tint | E6: common | F6: #CC7722
A7: TRACER_ASH | B7: 4 | C7: Tracer colour | D7: Ash Tracers | E7: common | F7: #B2B2B2
A8: SIGHT_SKY | B8: 5 | C8: Crosshair colour | D8: Sky Sights | E8: common | F8: #78B4E6
A9: FLAG_ROSE | B9: 6 | C9: Tower flag | D9: Rose Flag | E9: common | F9: #DC8296
A10: BANNER_FERN | B10: 7 | C10: Leaderboard banner | D10: Fern Banner | E10: common | F10: #4F7942
A11: NAME_MOSS | B11: 8 | C11: Name colour | D11: Moss Name | E11: common | F11: #8A9A5B
A12: TINT_RUST | B12: 9 | C12: Gun tint | D12: Rust Tint | E12: common | F12: #A04828
A13: HAT_BUSH | B13: 10 | C13: Hunting hat | D13: Bush Hat | E13: rare | F13: #6E7846 | G13: Fabric | H13: Brim
A14: TITLE_10 | B14: 10 | C14: Title | D14: Greenhorn | E14: title
A15: TRACER_SLATE | B15: 11 | C15: Tracer colour | D15: Slate Tracers | E15: common | F15: #586373
A16: SIGHT_DUSK | B16: 12 | C16: Crosshair colour | D16: Dusk Sights | E16: common | F16: #62508C
A17: FLAG_EMBER | B17: 13 | C17: Tower flag | D17: Ember Flag | E17: common | F17: #E65A32
A18: BANNER_MOSS | B18: 14 | C18: Leaderboard banner | D18: Moss Banner | E18: common | F18: #8A9A5B
A19: NAME_CLAY | B19: 15 | C19: Name colour | D19: Clay Name | E19: common | F19: #B0684A
A20: TINT_BONE | B20: 16 | C20: Gun tint | D20: Bone Tint | E20: common | F20: #E3DAC9
A21: TRACER_TEAL | B21: 17 | C21: Tracer colour | D21: Teal Tracers | E21: common | F21: #288080
A22: SIGHT_PLUM | B22: 18 | C22: Crosshair colour | D22: Plum Sights | E22: common | F22: #823C64
A23: FLAG_SAND | B23: 19 | C23: Tower flag | D23: Sand Flag | E23: common | F23: #C2B280
A24: GUN_IRONWOOD | B24: 20 | C24: Gun pattern | D24: Ironwood Stock | E24: rare | F24: #785032 | G24: Wood
A25: TITLE_20 | B25: 20 | C25: Title | D25: Trapper | E25: title
A26: BANNER_CLAY | B26: 21 | C26: Leaderboard banner | D26: Clay Banner | E26: common | F26: #B0684A
A27: NAME_OCHRE | B27: 22 | C27: Name colour | D27: Ochre Name | E27: common | F27: #CC7722
A28: TINT_ASH | B28: 23 | C28: Gun tint | D28: Ash Tint | E28: common | F28: #B2B2B2
A29: TRACER_SKY | B29: 24 | C29: Tracer colour | D29: Sky Tracers | E29: common | F29: #78B4E6
A30: SIGHT_ROSE | B30: 25 | C30: Crosshair colour | D30: Rose Sights | E30: common | F30: #DC8296
A31: FLAG_FERN | B31: 26 | C31: Tower flag | D31: Fern Flag | E31: common | F31: #4F7942
A32: BANNER_OCHRE | B32: 27 | C32: Leaderboard banner | D32: Ochre Banner | E32: common | F32: #CC7722
A33: NAME_RUST | B33: 28 | C33: Name colour | D33: Rust Name | E33: common | F33: #A04828
A34: TINT_SLATE | B34: 29 | C34: Gun tint | D34: Slate Tint | E34: common | F34: #586373
A35: MARK_TOOTH | B35: 30 | C35: Hit-marker | D35: Tooth Marker | E35: rare | F35: #EBE1BE | H35: Diamond
A36: TITLE_30 | B36: 30 | C36: Title | D36: Trailblazer | E36: title
A37: TRACER_DUSK | B37: 31 | C37: Tracer colour | D37: Dusk Tracers | E37: common | F37: #62508C
A38: SIGHT_EMBER | B38: 32 | C38: Crosshair colour | D38: Ember Sights | E38: common | F38: #E65A32
A39: FLAG_MOSS | B39: 33 | C39: Tower flag | D39: Moss Flag | E39: common | F39: #8A9A5B
A40: BANNER_RUST | B40: 34 | C40: Leaderboard banner | D40: Rust Banner | E40: common | F40: #A04828
A41: NAME_BONE | B41: 35 | C41: Name colour | D41: Bone Name | E41: common | F41: #E3DAC9
A42: TINT_TEAL | B42: 36 | C42: Gun tint | D42: Teal Tint | E42: common | F42: #288080
A43: TRACER_PLUM | B43: 37 | C43: Tracer colour | D43: Plum Tracers | E43: common | F43: #823C64
A44: SIGHT_SAND | B44: 38 | C44: Crosshair colour | D44: Sand Sights | E44: common | F44: #C2B280
A45: FLAG_CLAY | B45: 39 | C45: Tower flag | D45: Clay Flag | E45: common | F45: #B0684A
A46: TRAIL_DUST | B46: 40 | C46: Sprint trail | D46: Dust Trail | E46: rare | F46: #C2A078
A47: TITLE_40 | B47: 40 | C47: Title | D47: Ranger | E47: title
A48: BANNER_BONE | B48: 41 | C48: Leaderboard banner | D48: Bone Banner | E48: common | F48: #E3DAC9
A49: NAME_ASH | B49: 42 | C49: Name colour | D49: Ash Name | E49: common | F49: #B2B2B2
A50: TINT_SKY | B50: 43 | C50: Gun tint | D50: Sky Tint | E50: common | F50: #78B4E6
A51: TRACER_ROSE | B51: 44 | C51: Tracer colour | D51: Rose Tracers | E51: common | F51: #DC8296
A52: SIGHT_FERN | B52: 45 | C52: Crosshair colour | D52: Fern Sights | E52: common | F52: #4F7942
A53: FLAG_OCHRE | B53: 46 | C53: Tower flag | D53: Ochre Flag | E53: common | F53: #CC7722
A54: BANNER_ASH | B54: 47 | C54: Leaderboard banner | D54: Ash Banner | E54: common | F54: #B2B2B2
A55: NAME_SLATE | B55: 48 | C55: Name colour | D55: Slate Name | E55: common | F55: #586373
A56: TINT_DUSK | B56: 49 | C56: Gun tint | D56: Dusk Tint | E56: common | F56: #62508C
A57: HAT_RANGER | B57: 50 | C57: Hunting hat | D57: Ranger Cap | E57: rare | F57: #963C32 | G57: Fabric | H57: Cap
A58: TITLE_50 | B58: 50 | C58: Title | D58: Veteran Hunter | E58: title
A59: TRACER_EMBER | B59: 51 | C59: Tracer colour | D59: Ember Tracers | E59: common | F59: #E65A32
A60: SIGHT_MOSS | B60: 52 | C60: Crosshair colour | D60: Moss Sights | E60: common | F60: #8A9A5B
A61: FLAG_RUST | B61: 53 | C61: Tower flag | D61: Rust Flag | E61: common | F61: #A04828
A62: BANNER_SLATE | B62: 54 | C62: Leaderboard banner | D62: Slate Banner | E62: common | F62: #586373
A63: NAME_TEAL | B63: 55 | C63: Name colour | D63: Teal Name | E63: common | F63: #288080
A64: TINT_PLUM | B64: 56 | C64: Gun tint | D64: Plum Tint | E64: common | F64: #823C64
A65: TRACER_SAND | B65: 57 | C65: Tracer colour | D65: Sand Tracers | E65: common | F65: #C2B280
A66: SIGHT_CLAY | B66: 58 | C66: Crosshair colour | D66: Clay Sights | E66: common | F66: #B0684A
A67: FLAG_BONE | B67: 59 | C67: Tower flag | D67: Bone Flag | E67: common | F67: #E3DAC9
A68: GUN_BONE | B68: 60 | C68: Gun pattern | D68: Bone Inlay | E68: rare | F68: #E6DECD | G68: Marble
A69: TITLE_60 | B69: 60 | C69: Title | D69: Game Warden | E69: title
A70: BANNER_TEAL | B70: 61 | C70: Leaderboard banner | D70: Teal Banner | E70: common | F70: #288080
A71: NAME_SKY | B71: 62 | C71: Name colour | D71: Sky Name | E71: common | F71: #78B4E6
A72: TINT_ROSE | B72: 63 | C72: Gun tint | D72: Rose Tint | E72: common | F72: #DC8296
A73: TRACER_FERN | B73: 64 | C73: Tracer colour | D73: Fern Tracers | E73: common | F73: #4F7942
A74: SIGHT_OCHRE | B74: 65 | C74: Crosshair colour | D74: Ochre Sights | E74: common | F74: #CC7722
A75: FLAG_ASH | B75: 66 | C75: Tower flag | D75: Ash Flag | E75: common | F75: #B2B2B2
A76: BANNER_SKY | B76: 67 | C76: Leaderboard banner | D76: Sky Banner | E76: common | F76: #78B4E6
A77: NAME_DUSK | B77: 68 | C77: Name colour | D77: Dusk Name | E77: common | F77: #62508C
A78: TINT_EMBER | B78: 69 | C78: Gun tint | D78: Ember Tint | E78: common | F78: #E65A32
A79: MARK_STAR | B79: 70 | C79: Hit-marker | D79: Claw Marker | E79: rare | F79: #78C8F0 | H79: Star
A80: TITLE_70 | B80: 70 | C80: Title | D80: Pathfinder | E80: title
A81: TRACER_MOSS | B81: 71 | C81: Tracer colour | D81: Moss Tracers | E81: common | F81: #8A9A5B
A82: SIGHT_RUST | B82: 72 | C82: Crosshair colour | D82: Rust Sights | E82: common | F82: #A04828
A83: FLAG_SLATE | B83: 73 | C83: Tower flag | D83: Slate Flag | E83: common | F83: #586373
A84: BANNER_DUSK | B84: 74 | C84: Leaderboard banner | D84: Dusk Banner | E84: common | F84: #62508C
A85: NAME_PLUM | B85: 75 | C85: Name colour | D85: Plum Name | E85: common | F85: #823C64
A86: TINT_SAND | B86: 76 | C86: Gun tint | D86: Sand Tint | E86: common | F86: #C2B280
A87: TRACER_CLAY | B87: 77 | C87: Tracer colour | D87: Clay Tracers | E87: common | F87: #B0684A
A88: SIGHT_BONE | B88: 78 | C88: Crosshair colour | D88: Bone Sights | E88: common | F88: #E3DAC9
A89: FLAG_TEAL | B89: 79 | C89: Tower flag | D89: Teal Flag | E89: common | F89: #288080
A90: TRAIL_FERN | B90: 80 | C90: Sprint trail | D90: Footprint Trail | E90: rare | F90: #64AA5A
A91: TITLE_80 | B91: 80 | C91: Title | D91: Raptor Bane | E91: title
A92: BANNER_PLUM | B92: 81 | C92: Leaderboard banner | D92: Plum Banner | E92: common | F92: #823C64
A93: NAME_ROSE | B93: 82 | C93: Name colour | D93: Rose Name | E93: common | F93: #DC8296
A94: TINT_FERN | B94: 83 | C94: Gun tint | D94: Fern Tint | E94: common | F94: #4F7942
A95: TRACER_OCHRE | B95: 84 | C95: Tracer colour | D95: Ochre Tracers | E95: common | F95: #CC7722
A96: SIGHT_ASH | B96: 85 | C96: Crosshair colour | D96: Ash Sights | E96: common | F96: #B2B2B2
A97: FLAG_SKY | B97: 86 | C97: Tower flag | D97: Sky Flag | E97: common | F97: #78B4E6
A98: BANNER_ROSE | B98: 87 | C98: Leaderboard banner | D98: Rose Banner | E98: common | F98: #DC8296
A99: NAME_EMBER | B99: 88 | C99: Name colour | D99: Ember Name | E99: common | F99: #E65A32
A100: TINT_MOSS | B100: 89 | C100: Gun tint | D100: Moss Tint | E100: common | F100: #8A9A5B
A101: HAT_CREST | B101: 90 | C101: Hunting hat | D101: Crest Helm | E101: rare | F101: #6E737D | G101: Metal | H101: Crest
...

Sheet Arenas
A1: ARENAS — ranked Trophy gates (names: Dino review Round 16, DECISIONS #229; PLAN T81)
A2: One row per arena, lowest first. Floor = the Trophies that reach it; you never drop below the floor of the best arena you've reached, and never below 0 (DECISIONS #218). Floors run up from 0. Reward = a Cosmetics Id unlocked the first time you reach it, or blank (cosmetic or title only, never power). Keys are saved in profiles: never rename one.
A4: Key | B4: Name | C4: Floor | D4: Reward
A5: ARENA_1 | B5: Fern Gully | C5: 0
A6: ARENA_2 | B6: Raptor Ridge | C6: 300
A7: ARENA_3 | B7: Muddy Springs | C7: 600
A8: ARENA_4 | B8: Horn Canyon | C8: 1000
A9: ARENA_5 | B9: Volcano Rim | C9: 1500
A10: ARENA_6 | B10: Sky Cliffs | C10: 2000
A11: ARENA_7 | B11: Misty Jungle | C11: 3000
A12: ARENA_8 | B12: Rex Kingdom | C12: 4000
